{"v":"5.5.7","meta":{"g":"LottieFiles AE 0.1.20","a":"","k":"","d":"","tc":""},"fr":29.9700012207031,"ip":0,"op":149.000006068894,"w":1920,"h":1082,"nm":"Comp 1","ddd":0,"assets":[{"id":"comp_0","layers":[{"ddd":0,"ind":1,"ty":4,"nm":"Mini pie chart","sr":1,"ks":{"o":{"a":1,"k":[{"i":{"x":[0.833],"y":[0.837]},"o":{"x":[0.167],"y":[0.167]},"t":12,"s":[0]},{"i":{"x":[0.833],"y":[0.837]},"o":{"x":[0.167],"y":[0.17]},"t":13,"s":[6.381]},{"i":{"x":[0.833],"y":[0.837]},"o":{"x":[0.167],"y":[0.171]},"t":14,"s":[12.485]},{"i":{"x":[0.833],"y":[0.837]},"o":{"x":[0.167],"y":[0.171]},"t":15,"s":[18.317]},{"i":{"x":[0.833],"y":[0.837]},"o":{"x":[0.167],"y":[0.171]},"t":16,"s":[23.884]},{"i":{"x":[0.833],"y":[0.837]},"o":{"x":[0.167],"y":[0.171]},"t":17,"s":[29.193]},{"i":{"x":[0.833],"y":[0.837]},"o":{"x":[0.167],"y":[0.171]},"t":18,"s":[34.248]},{"i":{"x":[0.833],"y":[0.838]},"o":{"x":[0.167],"y":[0.171]},"t":19,"s":[39.057]},{"i":{"x":[0.833],"y":[0.838]},"o":{"x":[0.167],"y":[0.171]},"t":20,"s":[43.626]},{"i":{"x":[0.833],"y":[0.838]},"o":{"x":[0.167],"y":[0.171]},"t":21,"s":[47.961]},{"i":{"x":[0.833],"y":[0.838]},"o":{"x":[0.167],"y":[0.171]},"t":22,"s":[52.067]},{"i":{"x":[0.833],"y":[0.838]},"o":{"x":[0.167],"y":[0.172]},"t":23,"s":[55.952]},{"i":{"x":[0.833],"y":[0.838]},"o":{"x":[0.167],"y":[0.172]},"t":24,"s":[59.62]},{"i":{"x":[0.833],"y":[0.838]},"o":{"x":[0.167],"y":[0.172]},"t":25,"s":[63.079]},{"i":{"x":[0.833],"y":[0.839]},"o":{"x":[0.167],"y":[0.172]},"t":26,"s":[66.335]},{"i":{"x":[0.833],"y":[0.839]},"o":{"x":[0.167],"y":[0.172]},"t":27,"s":[69.394]},{"i":{"x":[0.833],"y":[0.839]},"o":{"x":[0.167],"y":[0.172]},"t":28,"s":[72.261]},{"i":{"x":[0.833],"y":[0.839]},"o":{"x":[0.167],"y":[0.173]},"t":29,"s":[74.943]},{"i":{"x":[0.833],"y":[0.839]},"o":{"x":[0.167],"y":[0.173]},"t":30,"s":[77.447]},{"i":{"x":[0.833],"y":[0.84]},"o":{"x":[0.167],"y":[0.173]},"t":31,"s":[79.778]},{"i":{"x":[0.833],"y":[0.84]},"o":{"x":[0.167],"y":[0.173]},"t":32,"s":[81.943]},{"i":{"x":[0.833],"y":[0.84]},"o":{"x":[0.167],"y":[0.174]},"t":33,"s":[83.947]},{"i":{"x":[0.833],"y":[0.84]},"o":{"x":[0.167],"y":[0.174]},"t":34,"s":[85.798]},{"i":{"x":[0.833],"y":[0.841]},"o":{"x":[0.167],"y":[0.174]},"t":35,"s":[87.5]},{"i":{"x":[0.833],"y":[0.841]},"o":{"x":[0.167],"y":[0.175]},"t":36,"s":[89.061]},{"i":{"x":[0.833],"y":[0.841]},"o":{"x":[0.167],"y":[0.175]},"t":37,"s":[90.486]},{"i":{"x":[0.833],"y":[0.842]},"o":{"x":[0.167],"y":[0.175]},"t":38,"s":[91.781]},{"i":{"x":[0.833],"y":[0.842]},"o":{"x":[0.167],"y":[0.176]},"t":39,"s":[92.953]},{"i":{"x":[0.833],"y":[0.843]},"o":{"x":[0.167],"y":[0.176]},"t":40,"s":[94.008]},{"i":{"x":[0.833],"y":[0.843]},"o":{"x":[0.167],"y":[0.177]},"t":41,"s":[94.953]},{"i":{"x":[0.833],"y":[0.844]},"o":{"x":[0.167],"y":[0.178]},"t":42,"s":[95.792]},{"i":{"x":[0.833],"y":[0.844]},"o":{"x":[0.167],"y":[0.179]},"t":43,"s":[96.533]},{"i":{"x":[0.833],"y":[0.845]},"o":{"x":[0.167],"y":[0.179]},"t":44,"s":[97.181]},{"i":{"x":[0.833],"y":[0.846]},"o":{"x":[0.167],"y":[0.181]},"t":45,"s":[97.743]},{"i":{"x":[0.833],"y":[0.847]},"o":{"x":[0.167],"y":[0.182]},"t":46,"s":[98.225]},{"i":{"x":[0.833],"y":[0.848]},"o":{"x":[0.167],"y":[0.183]},"t":47,"s":[98.633]},{"i":{"x":[0.833],"y":[0.85]},"o":{"x":[0.167],"y":[0.185]},"t":48,"s":[98.973]},{"i":{"x":[0.833],"y":[0.852]},"o":{"x":[0.167],"y":[0.187]},"t":49,"s":[99.251]},{"i":{"x":[0.833],"y":[0.854]},"o":{"x":[0.167],"y":[0.19]},"t":50,"s":[99.474]},{"i":{"x":[0.833],"y":[0.857]},"o":{"x":[0.167],"y":[0.194]},"t":51,"s":[99.648]},{"i":{"x":[0.833],"y":[0.861]},"o":{"x":[0.167],"y":[0.2]},"t":52,"s":[99.778]},{"i":{"x":[0.833],"y":[0.866]},"o":{"x":[0.167],"y":[0.208]},"t":53,"s":[99.872]},{"i":{"x":[0.833],"y":[0.874]},"o":{"x":[0.167],"y":[0.221]},"t":54,"s":[99.934]},{"i":{"x":[0.833],"y":[0.886]},"o":{"x":[0.167],"y":[0.246]},"t":55,"s":[99.972]},{"i":{"x":[0.833],"y":[0.905]},"o":{"x":[0.167],"y":[0.31]},"t":56,"s":[99.992]},{"i":{"x":[0.833],"y":[0.917]},"o":{"x":[0.167],"y":[0.667]},"t":57,"s":[99.999]},{"i":{"x":[0.833],"y":[1]},"o":{"x":[0.167],"y":[0]},"t":58,"s":[100]},{"i":{"x":[0.833],"y":[1]},"o":{"x":[0.167],"y":[0]},"t":59,"s":[100]},{"i":{"x":[0.833],"y":[1]},"o":{"x":[0.167],"y":[0]},"t":60,"s":[100]},{"i":{"x":[0.833],"y":[1]},"o":{"x":[0.167],"y":[0]},"t":61,"s":[100]},{"i":{"x":[0.833],"y":[1]},"o":{"x":[0.167],"y":[0]},"t":62,"s":[100]},{"i":{"x":[0.833],"y":[1]},"o":{"x":[0.167],"y":[0]},"t":63,"s":[100]},{"i":{"x":[0.833],"y":[1]},"o":{"x":[0.167],"y":[0]},"t":64,"s":[100]},{"i":{"x":[0.833],"y":[1]},"o":{"x":[0.167],"y":[0]},"t":65,"s":[100]},{"i":{"x":[0.833],"y":[1]},"o":{"x":[0.167],"y":[0]},"t":66,"s":[100]},{"i":{"x":[0.833],"y":[1]},"o":{"x":[0.167],"y":[0]},"t":67,"s":[100]},{"i":{"x":[0.833],"y":[1]},"o":{"x":[0.167],"y":[0]},"t":68,"s":[100]},{"i":{"x":[0.833],"y":[1]},"o":{"x":[0.167],"y":[0]},"t":69,"s":[100]},{"i":{"x":[0.833],"y":[1]},"o":{"x":[0.167],"y":[0]},"t":70,"s":[100]},{"i":{"x":[0.833],"y":[1]},"o":{"x":[0.167],"y":[0]},"t":71,"s":[100]},{"i":{"x":[0.833],"y":[1]},"o":{"x":[0.167],"y":[0]},"t":72,"s":[100]},{"i":{"x":[0.833],"y":[1]},"o":{"x":[0.167],"y":[0]},"t":73,"s":[100]},{"i":{"x":[0.833],"y":[1]},"o":{"x":[0.167],"y":[0]},"t":74,"s":[100]},{"i":{"x":[0.833],"y":[1]},"o":{"x":[0.167],"y":[0]},"t":75,"s":[100]},{"i":{"x":[0.833],"y":[1]},"o":{"x":[0.167],"y":[0]},"t":76,"s":[100]},{"i":{"x":[0.833],"y":[1]},"o":{"x":[0.167],"y":[0]},"t":77,"s":[100]},{"i":{"x":[0.833],"y":[1]},"o":{"x":[0.167],"y":[0]},"t":78,"s":[100]},{"i":{"x":[0.833],"y":[1]},"o":{"x":[0.167],"y":[0]},"t":79,"s":[100]},{"i":{"x":[0.833],"y":[1]},"o":{"x":[0.167],"y":[0]},"t":80,"s":[100]},{"i":{"x":[0.833],"y":[1]},"o":{"x":[0.167],"y":[0]},"t":81,"s":[100]},{"i":{"x":[0.833],"y":[1]},"o":{"x":[0.167],"y":[0]},"t":82,"s":[100]},{"i":{"x":[0.833],"y":[1]},"o":{"x":[0.167],"y":[0]},"t":83,"s":[100]},{"i":{"x":[0.833],"y":[1]},"o":{"x":[0.167],"y":[0]},"t":84,"s":[100]},{"i":{"x":[0.833],"y":[1]},"o":{"x":[0.167],"y":[0]},"t":85,"s":[100]},{"i":{"x":[0.833],"y":[1]},"o":{"x":[0.167],"y":[0]},"t":86,"s":[100]},{"i":{"x":[0.833],"y":[1]},"o":{"x":[0.167],"y":[0]},"t":87,"s":[100]},{"i":{"x":[0.833],"y":[1]},"o":{"x":[0.167],"y":[0]},"t":88,"s":[100]},{"i":{"x":[0.833],"y":[1]},"o":{"x":[0.167],"y":[0]},"t":89,"s":[100]},{"i":{"x":[0.833],"y":[1]},"o":{"x":[0.167],"y":[0]},"t":90,"s":[100]},{"i":{"x":[0.833],"y":[1]},"o":{"x":[0.167],"y":[0]},"t":91,"s":[100]},{"i":{"x":[0.833],"y":[1]},"o":{"x":[0.167],"y":[0]},"t":92,"s":[100]},{"i":{"x":[0.833],"y":[1]},"o":{"x":[0.167],"y":[0]},"t":93,"s":[100]},{"i":{"x":[0.833],"y":[1]},"o":{"x":[0.167],"y":[0]},"t":94,"s":[100]},{"i":{"x":[0.833],"y":[1]},"o":{"x":[0.167],"y":[0]},"t":95,"s":[100]},{"i":{"x":[0.833],"y":[1]},"o":{"x":[0.167],"y":[0]},"t":96,"s":[100]},{"i":{"x":[0.833],"y":[1]},"o":{"x":[0.167],"y":[0]},"t":97,"s":[100]},{"i":{"x":[0.833],"y":[1]},"o":{"x":[0.167],"y":[0]},"t":98,"s":[100]},{"i":{"x":[0.833],"y":[1]},"o":{"x":[0.167],"y":[0]},"t":99,"s":[100]},{"i":{"x":[0.833],"y":[1]},"o":{"x":[0.167],"y":[0]},"t":100,"s":[100]},{"i":{"x":[0.833],"y":[1]},"o":{"x":[0.167],"y":[0]},"t":101,"s":[100]},{"i":{"x":[0.833],"y":[1]},"o":{"x":[0.167],"y":[0]},"t":102,"s":[100]},{"i":{"x":[0.833],"y":[0.333]},"o":{"x":[0.167],"y":[0.083]},"t":103,"s":[100]},{"i":{"x":[0.833],"y":[0.69]},"o":{"x":[0.167],"y":[0.095]},"t":104,"s":[99.997]},{"i":{"x":[0.833],"y":[0.754]},"o":{"x":[0.167],"y":[0.114]},"t":105,"s":[99.98]},{"i":{"x":[0.833],"y":[0.779]},"o":{"x":[0.167],"y":[0.126]},"t":106,"s":[99.931]},{"i":{"x":[0.833],"y":[0.792]},"o":{"x":[0.167],"y":[0.134]},"t":107,"s":[99.837]},{"i":{"x":[0.833],"y":[0.8]},"o":{"x":[0.167],"y":[0.139]},"t":108,"s":[99.682]},{"i":{"x":[0.833],"y":[0.806]},"o":{"x":[0.167],"y":[0.143]},"t":109,"s":[99.45]},{"i":{"x":[0.833],"y":[0.81]},"o":{"x":[0.167],"y":[0.146]},"t":110,"s":[99.127]},{"i":{"x":[0.833],"y":[0.813]},"o":{"x":[0.167],"y":[0.148]},"t":111,"s":[98.697]},{"i":{"x":[0.833],"y":[0.815]},"o":{"x":[0.167],"y":[0.15]},"t":112,"s":[98.145]},{"i":{"x":[0.833],"y":[0.817]},"o":{"x":[0.167],"y":[0.152]},"t":113,"s":[97.456]},{"i":{"x":[0.833],"y":[0.818]},"o":{"x":[0.167],"y":[0.153]},"t":114,"s":[96.614]},{"i":{"x":[0.833],"y":[0.819]},"o":{"x":[0.167],"y":[0.154]},"t":115,"s":[95.604]},{"i":{"x":[0.833],"y":[0.821]},"o":{"x":[0.167],"y":[0.155]},"t":116,"s":[94.41]},{"i":{"x":[0.833],"y":[0.821]},"o":{"x":[0.167],"y":[0.156]},"t":117,"s":[93.019]},{"i":{"x":[0.833],"y":[0.822]},"o":{"x":[0.167],"y":[0.156]},"t":118,"s":[91.413]},{"i":{"x":[0.833],"y":[0.823]},"o":{"x":[0.167],"y":[0.157]},"t":119,"s":[89.579]},{"i":{"x":[0.833],"y":[0.824]},"o":{"x":[0.167],"y":[0.157]},"t":120,"s":[87.5]},{"i":{"x":[0.833],"y":[0.824]},"o":{"x":[0.167],"y":[0.158]},"t":121,"s":[85.162]},{"i":{"x":[0.833],"y":[0.825]},"o":{"x":[0.167],"y":[0.158]},"t":122,"s":[82.549]},{"i":{"x":[0.833],"y":[0.825]},"o":{"x":[0.167],"y":[0.159]},"t":123,"s":[79.646]},{"i":{"x":[0.833],"y":[0.825]},"o":{"x":[0.167],"y":[0.159]},"t":124,"s":[76.438]},{"i":{"x":[0.833],"y":[0.826]},"o":{"x":[0.167],"y":[0.159]},"t":125,"s":[72.909]},{"i":{"x":[0.833],"y":[0.826]},"o":{"x":[0.167],"y":[0.16]},"t":126,"s":[69.044]},{"i":{"x":[0.833],"y":[0.826]},"o":{"x":[0.167],"y":[0.16]},"t":127,"s":[64.828]},{"i":{"x":[0.833],"y":[0.827]},"o":{"x":[0.167],"y":[0.16]},"t":128,"s":[60.246]},{"i":{"x":[0.833],"y":[0.827]},"o":{"x":[0.167],"y":[0.16]},"t":129,"s":[55.282]},{"i":{"x":[0.833],"y":[0.827]},"o":{"x":[0.167],"y":[0.161]},"t":130,"s":[49.921]},{"i":{"x":[0.833],"y":[0.827]},"o":{"x":[0.167],"y":[0.161]},"t":131,"s":[44.148]},{"i":{"x":[0.833],"y":[0.828]},"o":{"x":[0.167],"y":[0.161]},"t":132,"s":[37.948]},{"i":{"x":[0.833],"y":[0.828]},"o":{"x":[0.167],"y":[0.161]},"t":133,"s":[31.305]},{"i":{"x":[0.833],"y":[0.828]},"o":{"x":[0.167],"y":[0.161]},"t":134,"s":[24.204]},{"i":{"x":[0.833],"y":[0.828]},"o":{"x":[0.167],"y":[0.162]},"t":135,"s":[16.629]},{"i":{"x":[0.833],"y":[0.833]},"o":{"x":[0.167],"y":[0.162]},"t":136,"s":[8.567]},{"t":137.000005580124,"s":[0]}],"ix":11},"r":{"a":0,"k":0,"ix":10},"p":{"a":0,"k":[734,100,0],"ix":2},"a":{"a":0,"k":[108.5,52,0],"ix":1},"s":{"a":0,"k":[160.947,160.947,100],"ix":6}},"ao":0,"shapes":[{"ty":"gr","it":[{"ind":0,"ty":"sh","ix":1,"ks":{"a":0,"k":{"i":[[0.001,0.654],[-0.003,0.054],[-20.047,18.795],[-27.552,0.063],[-20.135,-18.703],[-1.813,-27.34],[0.114,-0.319],[0.236,-0.247],[0.311,-0.134],[0.338,0],[0,0],[0.465,0.461]],"o":[[0,-0.053],[1.684,-27.347],[20.048,-18.796],[27.553,-0.064],[20.134,18.703],[0.022,0.338],[-0.118,0.32],[-0.227,0.246],[-0.311,0.134],[0,0],[-0.657,0],[-0.464,-0.462]],"v":[[-108.162,49.439],[-108.158,49.278],[-74.33,-22.546],[-0.235,-51.901],[73.996,-22.887],[108.158,48.783],[108.021,49.779],[107.49,50.638],[106.675,51.214],[105.693,51.417],[-105.681,51.901],[-107.434,51.181]],"c":true},"ix":2},"nm":"Path 1","mn":"ADBE Vector Shape - Group","hd":false},{"ty":"fl","c":{"a":0,"k":[0.245965770647,0.704548076555,0.884769215303,1],"ix":4},"o":{"a":0,"k":100,"ix":5},"r":1,"bm":0,"nm":"Fill 1","mn":"ADBE Vector Graphic - Fill","hd":false},{"ty":"tr","p":{"a":0,"k":[108.163,51.901],"ix":2},"a":{"a":0,"k":[0,0],"ix":1},"s":{"a":0,"k":[100,100],"ix":3},"r":{"a":0,"k":0,"ix":6},"o":{"a":0,"k":100,"ix":7},"sk":{"a":0,"k":0,"ix":4},"sa":{"a":0,"k":0,"ix":5},"nm":"Transform"}],"nm":"Group 1","np":4,"cix":2,"bm":0,"ix":1,"mn":"ADBE Vector Group","hd":false}],"ip":12.00000048877,"op":138.000005620855,"st":-53.0000021587343,"bm":0},{"ddd":0,"ind":2,"ty":4,"nm":"Mini Pie chart","sr":1,"ks":{"o":{"a":1,"k":[{"i":{"x":[0.833],"y":[0.837]},"o":{"x":[0.167],"y":[0.167]},"t":12,"s":[0]},{"i":{"x":[0.833],"y":[0.837]},"o":{"x":[0.167],"y":[0.17]},"t":13,"s":[6.248]},{"i":{"x":[0.833],"y":[0.837]},"o":{"x":[0.167],"y":[0.17]},"t":14,"s":[12.23]},{"i":{"x":[0.833],"y":[0.837]},"o":{"x":[0.167],"y":[0.171]},"t":15,"s":[17.953]},{"i":{"x":[0.833],"y":[0.837]},"o":{"x":[0.167],"y":[0.171]},"t":16,"s":[23.421]},{"i":{"x":[0.833],"y":[0.837]},"o":{"x":[0.167],"y":[0.171]},"t":17,"s":[28.64]},{"i":{"x":[0.833],"y":[0.837]},"o":{"x":[0.167],"y":[0.171]},"t":18,"s":[33.617]},{"i":{"x":[0.833],"y":[0.837]},"o":{"x":[0.167],"y":[0.171]},"t":19,"s":[38.357]},{"i":{"x":[0.833],"y":[0.838]},"o":{"x":[0.167],"y":[0.171]},"t":20,"s":[42.865]},{"i":{"x":[0.833],"y":[0.838]},"o":{"x":[0.167],"y":[0.171]},"t":21,"s":[47.149]},{"i":{"x":[0.833],"y":[0.838]},"o":{"x":[0.167],"y":[0.171]},"t":22,"s":[51.212]},{"i":{"x":[0.833],"y":[0.838]},"o":{"x":[0.167],"y":[0.171]},"t":23,"s":[55.062]},{"i":{"x":[0.833],"y":[0.838]},"o":{"x":[0.167],"y":[0.172]},"t":24,"s":[58.704]},{"i":{"x":[0.833],"y":[0.838]},"o":{"x":[0.167],"y":[0.172]},"t":25,"s":[62.143]},{"i":{"x":[0.833],"y":[0.838]},"o":{"x":[0.167],"y":[0.172]},"t":26,"s":[65.386]},{"i":{"x":[0.833],"y":[0.839]},"o":{"x":[0.167],"y":[0.172]},"t":27,"s":[68.439]},{"i":{"x":[0.833],"y":[0.839]},"o":{"x":[0.167],"y":[0.172]},"t":28,"s":[71.306]},{"i":{"x":[0.833],"y":[0.839]},"o":{"x":[0.167],"y":[0.172]},"t":29,"s":[73.994]},{"i":{"x":[0.833],"y":[0.839]},"o":{"x":[0.167],"y":[0.173]},"t":30,"s":[76.509]},{"i":{"x":[0.833],"y":[0.839]},"o":{"x":[0.167],"y":[0.173]},"t":31,"s":[78.856]},{"i":{"x":[0.833],"y":[0.84]},"o":{"x":[0.167],"y":[0.173]},"t":32,"s":[81.042]},{"i":{"x":[0.833],"y":[0.84]},"o":{"x":[0.167],"y":[0.173]},"t":33,"s":[83.071]},{"i":{"x":[0.833],"y":[0.84]},"o":{"x":[0.167],"y":[0.174]},"t":34,"s":[84.95]},{"i":{"x":[0.833],"y":[0.84]},"o":{"x":[0.167],"y":[0.174]},"t":35,"s":[86.685]},{"i":{"x":[0.833],"y":[0.841]},"o":{"x":[0.167],"y":[0.174]},"t":36,"s":[88.281]},{"i":{"x":[0.833],"y":[0.841]},"o":{"x":[0.167],"y":[0.175]},"t":37,"s":[89.744]},{"i":{"x":[0.833],"y":[0.841]},"o":{"x":[0.167],"y":[0.175]},"t":38,"s":[91.08]},{"i":{"x":[0.833],"y":[0.842]},"o":{"x":[0.167],"y":[0.175]},"t":39,"s":[92.295]},{"i":{"x":[0.833],"y":[0.842]},"o":{"x":[0.167],"y":[0.176]},"t":40,"s":[93.394]},{"i":{"x":[0.833],"y":[0.843]},"o":{"x":[0.167],"y":[0.176]},"t":41,"s":[94.383]},{"i":{"x":[0.833],"y":[0.843]},"o":{"x":[0.167],"y":[0.177]},"t":42,"s":[95.268]},{"i":{"x":[0.833],"y":[0.844]},"o":{"x":[0.167],"y":[0.178]},"t":43,"s":[96.055]},{"i":{"x":[0.833],"y":[0.844]},"o":{"x":[0.167],"y":[0.179]},"t":44,"s":[96.749]},{"i":{"x":[0.833],"y":[0.845]},"o":{"x":[0.167],"y":[0.179]},"t":45,"s":[97.357]},{"i":{"x":[0.833],"y":[0.846]},"o":{"x":[0.167],"y":[0.181]},"t":46,"s":[97.884]},{"i":{"x":[0.833],"y":[0.847]},"o":{"x":[0.167],"y":[0.182]},"t":47,"s":[98.336]},{"i":{"x":[0.833],"y":[0.848]},"o":{"x":[0.167],"y":[0.183]},"t":48,"s":[98.718]},{"i":{"x":[0.833],"y":[0.85]},"o":{"x":[0.167],"y":[0.185]},"t":49,"s":[99.037]},{"i":{"x":[0.833],"y":[0.852]},"o":{"x":[0.167],"y":[0.187]},"t":50,"s":[99.298]},{"i":{"x":[0.833],"y":[0.854]},"o":{"x":[0.167],"y":[0.19]},"t":51,"s":[99.507]},{"i":{"x":[0.833],"y":[0.857]},"o":{"x":[0.167],"y":[0.194]},"t":52,"s":[99.67]},{"i":{"x":[0.833],"y":[0.861]},"o":{"x":[0.167],"y":[0.2]},"t":53,"s":[99.792]},{"i":{"x":[0.833],"y":[0.866]},"o":{"x":[0.167],"y":[0.208]},"t":54,"s":[99.88]},{"i":{"x":[0.833],"y":[0.874]},"o":{"x":[0.167],"y":[0.221]},"t":55,"s":[99.938]},{"i":{"x":[0.833],"y":[0.886]},"o":{"x":[0.167],"y":[0.246]},"t":56,"s":[99.974]},{"i":{"x":[0.833],"y":[0.905]},"o":{"x":[0.167],"y":[0.31]},"t":57,"s":[99.992]},{"i":{"x":[0.833],"y":[0.917]},"o":{"x":[0.167],"y":[0.667]},"t":58,"s":[99.999]},{"i":{"x":[0.833],"y":[1]},"o":{"x":[0.167],"y":[0]},"t":59,"s":[100]},{"i":{"x":[0.833],"y":[1]},"o":{"x":[0.167],"y":[0]},"t":60,"s":[100]},{"i":{"x":[0.833],"y":[1]},"o":{"x":[0.167],"y":[0]},"t":61,"s":[100]},{"i":{"x":[0.833],"y":[1]},"o":{"x":[0.167],"y":[0]},"t":62,"s":[100]},{"i":{"x":[0.833],"y":[1]},"o":{"x":[0.167],"y":[0]},"t":63,"s":[100]},{"i":{"x":[0.833],"y":[1]},"o":{"x":[0.167],"y":[0]},"t":64,"s":[100]},{"i":{"x":[0.833],"y":[1]},"o":{"x":[0.167],"y":[0]},"t":65,"s":[100]},{"i":{"x":[0.833],"y":[1]},"o":{"x":[0.167],"y":[0]},"t":66,"s":[100]},{"i":{"x":[0.833],"y":[1]},"o":{"x":[0.167],"y":[0]},"t":67,"s":[100]},{"i":{"x":[0.833],"y":[1]},"o":{"x":[0.167],"y":[0]},"t":68,"s":[100]},{"i":{"x":[0.833],"y":[1]},"o":{"x":[0.167],"y":[0]},"t":69,"s":[100]},{"i":{"x":[0.833],"y":[1]},"o":{"x":[0.167],"y":[0]},"t":70,"s":[100]},{"i":{"x":[0.833],"y":[1]},"o":{"x":[0.167],"y":[0]},"t":71,"s":[100]},{"i":{"x":[0.833],"y":[1]},"o":{"x":[0.167],"y":[0]},"t":72,"s":[100]},{"i":{"x":[0.833],"y":[1]},"o":{"x":[0.167],"y":[0]},"t":73,"s":[100]},{"i":{"x":[0.833],"y":[1]},"o":{"x":[0.167],"y":[0]},"t":74,"s":[100]},{"i":{"x":[0.833],"y":[1]},"o":{"x":[0.167],"y":[0]},"t":75,"s":[100]},{"i":{"x":[0.833],"y":[1]},"o":{"x":[0.167],"y":[0]},"t":76,"s":[100]},{"i":{"x":[0.833],"y":[1]},"o":{"x":[0.167],"y":[0]},"t":77,"s":[100]},{"i":{"x":[0.833],"y":[1]},"o":{"x":[0.167],"y":[0]},"t":78,"s":[100]},{"i":{"x":[0.833],"y":[1]},"o":{"x":[0.167],"y":[0]},"t":79,"s":[100]},{"i":{"x":[0.833],"y":[1]},"o":{"x":[0.167],"y":[0]},"t":80,"s":[100]},{"i":{"x":[0.833],"y":[1]},"o":{"x":[0.167],"y":[0]},"t":81,"s":[100]},{"i":{"x":[0.833],"y":[1]},"o":{"x":[0.167],"y":[0]},"t":82,"s":[100]},{"i":{"x":[0.833],"y":[1]},"o":{"x":[0.167],"y":[0]},"t":83,"s":[100]},{"i":{"x":[0.833],"y":[1]},"o":{"x":[0.167],"y":[0]},"t":84,"s":[100]},{"i":{"x":[0.833],"y":[1]},"o":{"x":[0.167],"y":[0]},"t":85,"s":[100]},{"i":{"x":[0.833],"y":[1]},"o":{"x":[0.167],"y":[0]},"t":86,"s":[100]},{"i":{"x":[0.833],"y":[1]},"o":{"x":[0.167],"y":[0]},"t":87,"s":[100]},{"i":{"x":[0.833],"y":[1]},"o":{"x":[0.167],"y":[0]},"t":88,"s":[100]},{"i":{"x":[0.833],"y":[1]},"o":{"x":[0.167],"y":[0]},"t":89,"s":[100]},{"i":{"x":[0.833],"y":[1]},"o":{"x":[0.167],"y":[0]},"t":90,"s":[100]},{"i":{"x":[0.833],"y":[1]},"o":{"x":[0.167],"y":[0]},"t":91,"s":[100]},{"i":{"x":[0.833],"y":[1]},"o":{"x":[0.167],"y":[0]},"t":92,"s":[100]},{"i":{"x":[0.833],"y":[1]},"o":{"x":[0.167],"y":[0]},"t":93,"s":[100]},{"i":{"x":[0.833],"y":[1]},"o":{"x":[0.167],"y":[0]},"t":94,"s":[100]},{"i":{"x":[0.833],"y":[1]},"o":{"x":[0.167],"y":[0]},"t":95,"s":[100]},{"i":{"x":[0.833],"y":[1]},"o":{"x":[0.167],"y":[0]},"t":96,"s":[100]},{"i":{"x":[0.833],"y":[1]},"o":{"x":[0.167],"y":[0]},"t":97,"s":[100]},{"i":{"x":[0.833],"y":[1]},"o":{"x":[0.167],"y":[0]},"t":98,"s":[100]},{"i":{"x":[0.833],"y":[1]},"o":{"x":[0.167],"y":[0]},"t":99,"s":[100]},{"i":{"x":[0.833],"y":[1]},"o":{"x":[0.167],"y":[0]},"t":100,"s":[100]},{"i":{"x":[0.833],"y":[1]},"o":{"x":[0.167],"y":[0]},"t":101,"s":[100]},{"i":{"x":[0.833],"y":[1]},"o":{"x":[0.167],"y":[0]},"t":102,"s":[100]},{"i":{"x":[0.833],"y":[0.333]},"o":{"x":[0.167],"y":[0.083]},"t":103,"s":[100]},{"i":{"x":[0.833],"y":[0.69]},"o":{"x":[0.167],"y":[0.095]},"t":104,"s":[99.997]},{"i":{"x":[0.833],"y":[0.754]},"o":{"x":[0.167],"y":[0.114]},"t":105,"s":[99.98]},{"i":{"x":[0.833],"y":[0.779]},"o":{"x":[0.167],"y":[0.126]},"t":106,"s":[99.931]},{"i":{"x":[0.833],"y":[0.792]},"o":{"x":[0.167],"y":[0.134]},"t":107,"s":[99.837]},{"i":{"x":[0.833],"y":[0.8]},"o":{"x":[0.167],"y":[0.139]},"t":108,"s":[99.682]},{"i":{"x":[0.833],"y":[0.806]},"o":{"x":[0.167],"y":[0.143]},"t":109,"s":[99.45]},{"i":{"x":[0.833],"y":[0.81]},"o":{"x":[0.167],"y":[0.146]},"t":110,"s":[99.127]},{"i":{"x":[0.833],"y":[0.813]},"o":{"x":[0.167],"y":[0.148]},"t":111,"s":[98.697]},{"i":{"x":[0.833],"y":[0.815]},"o":{"x":[0.167],"y":[0.15]},"t":112,"s":[98.145]},{"i":{"x":[0.833],"y":[0.817]},"o":{"x":[0.167],"y":[0.152]},"t":113,"s":[97.456]},{"i":{"x":[0.833],"y":[0.818]},"o":{"x":[0.167],"y":[0.153]},"t":114,"s":[96.614]},{"i":{"x":[0.833],"y":[0.819]},"o":{"x":[0.167],"y":[0.154]},"t":115,"s":[95.604]},{"i":{"x":[0.833],"y":[0.821]},"o":{"x":[0.167],"y":[0.155]},"t":116,"s":[94.41]},{"i":{"x":[0.833],"y":[0.821]},"o":{"x":[0.167],"y":[0.156]},"t":117,"s":[93.019]},{"i":{"x":[0.833],"y":[0.822]},"o":{"x":[0.167],"y":[0.156]},"t":118,"s":[91.413]},{"i":{"x":[0.833],"y":[0.823]},"o":{"x":[0.167],"y":[0.157]},"t":119,"s":[89.579]},{"i":{"x":[0.833],"y":[0.824]},"o":{"x":[0.167],"y":[0.157]},"t":120,"s":[87.5]},{"i":{"x":[0.833],"y":[0.824]},"o":{"x":[0.167],"y":[0.158]},"t":121,"s":[85.162]},{"i":{"x":[0.833],"y":[0.825]},"o":{"x":[0.167],"y":[0.158]},"t":122,"s":[82.549]},{"i":{"x":[0.833],"y":[0.825]},"o":{"x":[0.167],"y":[0.159]},"t":123,"s":[79.646]},{"i":{"x":[0.833],"y":[0.825]},"o":{"x":[0.167],"y":[0.159]},"t":124,"s":[76.438]},{"i":{"x":[0.833],"y":[0.826]},"o":{"x":[0.167],"y":[0.159]},"t":125,"s":[72.909]},{"i":{"x":[0.833],"y":[0.826]},"o":{"x":[0.167],"y":[0.16]},"t":126,"s":[69.044]},{"i":{"x":[0.833],"y":[0.826]},"o":{"x":[0.167],"y":[0.16]},"t":127,"s":[64.828]},{"i":{"x":[0.833],"y":[0.827]},"o":{"x":[0.167],"y":[0.16]},"t":128,"s":[60.246]},{"i":{"x":[0.833],"y":[0.827]},"o":{"x":[0.167],"y":[0.16]},"t":129,"s":[55.282]},{"i":{"x":[0.833],"y":[0.827]},"o":{"x":[0.167],"y":[0.161]},"t":130,"s":[49.921]},{"i":{"x":[0.833],"y":[0.827]},"o":{"x":[0.167],"y":[0.161]},"t":131,"s":[44.148]},{"i":{"x":[0.833],"y":[0.828]},"o":{"x":[0.167],"y":[0.161]},"t":132,"s":[37.948]},{"i":{"x":[0.833],"y":[0.828]},"o":{"x":[0.167],"y":[0.161]},"t":133,"s":[31.305]},{"i":{"x":[0.833],"y":[0.828]},"o":{"x":[0.167],"y":[0.161]},"t":134,"s":[24.204]},{"i":{"x":[0.833],"y":[0.828]},"o":{"x":[0.167],"y":[0.162]},"t":135,"s":[16.629]},{"i":{"x":[0.833],"y":[0.833]},"o":{"x":[0.167],"y":[0.162]},"t":136,"s":[8.567]},{"t":137.000005580124,"s":[0]}],"ix":11},"r":{"a":0,"k":0,"ix":10},"p":{"a":0,"k":[828,252,0],"ix":2},"a":{"a":0,"k":[49,35.5,0],"ix":1},"s":{"a":0,"k":[165.306,165.306,100],"ix":6}},"ao":0,"shapes":[{"ty":"gr","it":[{"ind":0,"ty":"sh","ix":1,"ks":{"a":0,"k":{"i":[[0,0.065],[0.557,0.59],[0.398,0.171],[0.436,-0.002],[0,0],[0.524,-0.349],[0.24,-0.579],[-0.124,-0.614],[-0.448,-0.442],[0,0],[-0.402,-0.158],[-0.432,0.012],[-0.39,0.18],[-0.288,0.321],[-1.524,24.472]],"o":[[-0.004,-0.81],[-0.296,-0.316],[-0.401,-0.171],[0,0],[-0.63,0.002],[-0.523,0.349],[-0.24,0.579],[0.125,0.613],[0,0],[0.307,0.303],[0.402,0.159],[0.432,-0.013],[0.395,-0.181],[16.477,-18.259],[0.004,-0.066]],"v":[[48.98,-32.028],[48.104,-34.206],[47.046,-34.945],[45.777,-35.201],[-45.799,-34.992],[-47.57,-34.454],[-48.74,-33.03],[-48.917,-31.2],[-48.04,-29.581],[16.551,34.278],[17.628,34.978],[18.893,35.2],[20.145,34.908],[21.18,34.148],[48.973,-31.831]],"c":true},"ix":2},"nm":"Path 1","mn":"ADBE Vector Shape - Group","hd":false},{"ty":"fl","c":{"a":0,"k":[0.974557674632,0.831324797986,0.178477478027,1],"ix":4},"o":{"a":0,"k":100,"ix":5},"r":1,"bm":0,"nm":"Fill 1","mn":"ADBE Vector Graphic - Fill","hd":false},{"ty":"tr","p":{"a":0,"k":[48.98,35.201],"ix":2},"a":{"a":0,"k":[0,0],"ix":1},"s":{"a":0,"k":[100,100],"ix":3},"r":{"a":0,"k":0,"ix":6},"o":{"a":0,"k":100,"ix":7},"sk":{"a":0,"k":0,"ix":4},"sa":{"a":0,"k":0,"ix":5},"nm":"Transform"}],"nm":"Group 1","np":4,"cix":2,"bm":0,"ix":1,"mn":"ADBE Vector Group","hd":false}],"ip":12.00000048877,"op":138.000005620855,"st":-53.0000021587343,"bm":0},{"ddd":0,"ind":3,"ty":4,"nm":"Mini Pie Chart","sr":1,"ks":{"o":{"a":1,"k":[{"i":{"x":[0.833],"y":[0.837]},"o":{"x":[0.167],"y":[0.167]},"t":12,"s":[0]},{"i":{"x":[0.833],"y":[0.837]},"o":{"x":[0.167],"y":[0.17]},"t":13,"s":[6.248]},{"i":{"x":[0.833],"y":[0.837]},"o":{"x":[0.167],"y":[0.17]},"t":14,"s":[12.23]},{"i":{"x":[0.833],"y":[0.837]},"o":{"x":[0.167],"y":[0.171]},"t":15,"s":[17.953]},{"i":{"x":[0.833],"y":[0.837]},"o":{"x":[0.167],"y":[0.171]},"t":16,"s":[23.421]},{"i":{"x":[0.833],"y":[0.837]},"o":{"x":[0.167],"y":[0.171]},"t":17,"s":[28.64]},{"i":{"x":[0.833],"y":[0.837]},"o":{"x":[0.167],"y":[0.171]},"t":18,"s":[33.617]},{"i":{"x":[0.833],"y":[0.837]},"o":{"x":[0.167],"y":[0.171]},"t":19,"s":[38.357]},{"i":{"x":[0.833],"y":[0.838]},"o":{"x":[0.167],"y":[0.171]},"t":20,"s":[42.865]},{"i":{"x":[0.833],"y":[0.838]},"o":{"x":[0.167],"y":[0.171]},"t":21,"s":[47.149]},{"i":{"x":[0.833],"y":[0.838]},"o":{"x":[0.167],"y":[0.171]},"t":22,"s":[51.212]},{"i":{"x":[0.833],"y":[0.838]},"o":{"x":[0.167],"y":[0.171]},"t":23,"s":[55.062]},{"i":{"x":[0.833],"y":[0.838]},"o":{"x":[0.167],"y":[0.172]},"t":24,"s":[58.704]},{"i":{"x":[0.833],"y":[0.838]},"o":{"x":[0.167],"y":[0.172]},"t":25,"s":[62.143]},{"i":{"x":[0.833],"y":[0.838]},"o":{"x":[0.167],"y":[0.172]},"t":26,"s":[65.386]},{"i":{"x":[0.833],"y":[0.839]},"o":{"x":[0.167],"y":[0.172]},"t":27,"s":[68.439]},{"i":{"x":[0.833],"y":[0.839]},"o":{"x":[0.167],"y":[0.172]},"t":28,"s":[71.306]},{"i":{"x":[0.833],"y":[0.839]},"o":{"x":[0.167],"y":[0.172]},"t":29,"s":[73.994]},{"i":{"x":[0.833],"y":[0.839]},"o":{"x":[0.167],"y":[0.173]},"t":30,"s":[76.509]},{"i":{"x":[0.833],"y":[0.839]},"o":{"x":[0.167],"y":[0.173]},"t":31,"s":[78.856]},{"i":{"x":[0.833],"y":[0.84]},"o":{"x":[0.167],"y":[0.173]},"t":32,"s":[81.042]},{"i":{"x":[0.833],"y":[0.84]},"o":{"x":[0.167],"y":[0.173]},"t":33,"s":[83.071]},{"i":{"x":[0.833],"y":[0.84]},"o":{"x":[0.167],"y":[0.174]},"t":34,"s":[84.95]},{"i":{"x":[0.833],"y":[0.84]},"o":{"x":[0.167],"y":[0.174]},"t":35,"s":[86.685]},{"i":{"x":[0.833],"y":[0.841]},"o":{"x":[0.167],"y":[0.174]},"t":36,"s":[88.281]},{"i":{"x":[0.833],"y":[0.841]},"o":{"x":[0.167],"y":[0.175]},"t":37,"s":[89.744]},{"i":{"x":[0.833],"y":[0.841]},"o":{"x":[0.167],"y":[0.175]},"t":38,"s":[91.08]},{"i":{"x":[0.833],"y":[0.842]},"o":{"x":[0.167],"y":[0.175]},"t":39,"s":[92.295]},{"i":{"x":[0.833],"y":[0.842]},"o":{"x":[0.167],"y":[0.176]},"t":40,"s":[93.394]},{"i":{"x":[0.833],"y":[0.843]},"o":{"x":[0.167],"y":[0.176]},"t":41,"s":[94.383]},{"i":{"x":[0.833],"y":[0.843]},"o":{"x":[0.167],"y":[0.177]},"t":42,"s":[95.268]},{"i":{"x":[0.833],"y":[0.844]},"o":{"x":[0.167],"y":[0.178]},"t":43,"s":[96.055]},{"i":{"x":[0.833],"y":[0.844]},"o":{"x":[0.167],"y":[0.179]},"t":44,"s":[96.749]},{"i":{"x":[0.833],"y":[0.845]},"o":{"x":[0.167],"y":[0.179]},"t":45,"s":[97.357]},{"i":{"x":[0.833],"y":[0.846]},"o":{"x":[0.167],"y":[0.181]},"t":46,"s":[97.884]},{"i":{"x":[0.833],"y":[0.847]},"o":{"x":[0.167],"y":[0.182]},"t":47,"s":[98.336]},{"i":{"x":[0.833],"y":[0.848]},"o":{"x":[0.167],"y":[0.183]},"t":48,"s":[98.718]},{"i":{"x":[0.833],"y":[0.85]},"o":{"x":[0.167],"y":[0.185]},"t":49,"s":[99.037]},{"i":{"x":[0.833],"y":[0.852]},"o":{"x":[0.167],"y":[0.187]},"t":50,"s":[99.298]},{"i":{"x":[0.833],"y":[0.854]},"o":{"x":[0.167],"y":[0.19]},"t":51,"s":[99.507]},{"i":{"x":[0.833],"y":[0.857]},"o":{"x":[0.167],"y":[0.194]},"t":52,"s":[99.67]},{"i":{"x":[0.833],"y":[0.861]},"o":{"x":[0.167],"y":[0.2]},"t":53,"s":[99.792]},{"i":{"x":[0.833],"y":[0.866]},"o":{"x":[0.167],"y":[0.208]},"t":54,"s":[99.88]},{"i":{"x":[0.833],"y":[0.874]},"o":{"x":[0.167],"y":[0.221]},"t":55,"s":[99.938]},{"i":{"x":[0.833],"y":[0.886]},"o":{"x":[0.167],"y":[0.246]},"t":56,"s":[99.974]},{"i":{"x":[0.833],"y":[0.905]},"o":{"x":[0.167],"y":[0.31]},"t":57,"s":[99.992]},{"i":{"x":[0.833],"y":[0.917]},"o":{"x":[0.167],"y":[0.667]},"t":58,"s":[99.999]},{"i":{"x":[0.833],"y":[1]},"o":{"x":[0.167],"y":[0]},"t":59,"s":[100]},{"i":{"x":[0.833],"y":[1]},"o":{"x":[0.167],"y":[0]},"t":60,"s":[100]},{"i":{"x":[0.833],"y":[1]},"o":{"x":[0.167],"y":[0]},"t":61,"s":[100]},{"i":{"x":[0.833],"y":[1]},"o":{"x":[0.167],"y":[0]},"t":62,"s":[100]},{"i":{"x":[0.833],"y":[1]},"o":{"x":[0.167],"y":[0]},"t":63,"s":[100]},{"i":{"x":[0.833],"y":[1]},"o":{"x":[0.167],"y":[0]},"t":64,"s":[100]},{"i":{"x":[0.833],"y":[1]},"o":{"x":[0.167],"y":[0]},"t":65,"s":[100]},{"i":{"x":[0.833],"y":[1]},"o":{"x":[0.167],"y":[0]},"t":66,"s":[100]},{"i":{"x":[0.833],"y":[1]},"o":{"x":[0.167],"y":[0]},"t":67,"s":[100]},{"i":{"x":[0.833],"y":[1]},"o":{"x":[0.167],"y":[0]},"t":68,"s":[100]},{"i":{"x":[0.833],"y":[1]},"o":{"x":[0.167],"y":[0]},"t":69,"s":[100]},{"i":{"x":[0.833],"y":[1]},"o":{"x":[0.167],"y":[0]},"t":70,"s":[100]},{"i":{"x":[0.833],"y":[1]},"o":{"x":[0.167],"y":[0]},"t":71,"s":[100]},{"i":{"x":[0.833],"y":[1]},"o":{"x":[0.167],"y":[0]},"t":72,"s":[100]},{"i":{"x":[0.833],"y":[1]},"o":{"x":[0.167],"y":[0]},"t":73,"s":[100]},{"i":{"x":[0.833],"y":[1]},"o":{"x":[0.167],"y":[0]},"t":74,"s":[100]},{"i":{"x":[0.833],"y":[1]},"o":{"x":[0.167],"y":[0]},"t":75,"s":[100]},{"i":{"x":[0.833],"y":[1]},"o":{"x":[0.167],"y":[0]},"t":76,"s":[100]},{"i":{"x":[0.833],"y":[1]},"o":{"x":[0.167],"y":[0]},"t":77,"s":[100]},{"i":{"x":[0.833],"y":[1]},"o":{"x":[0.167],"y":[0]},"t":78,"s":[100]},{"i":{"x":[0.833],"y":[1]},"o":{"x":[0.167],"y":[0]},"t":79,"s":[100]},{"i":{"x":[0.833],"y":[1]},"o":{"x":[0.167],"y":[0]},"t":80,"s":[100]},{"i":{"x":[0.833],"y":[1]},"o":{"x":[0.167],"y":[0]},"t":81,"s":[100]},{"i":{"x":[0.833],"y":[1]},"o":{"x":[0.167],"y":[0]},"t":82,"s":[100]},{"i":{"x":[0.833],"y":[1]},"o":{"x":[0.167],"y":[0]},"t":83,"s":[100]},{"i":{"x":[0.833],"y":[1]},"o":{"x":[0.167],"y":[0]},"t":84,"s":[100]},{"i":{"x":[0.833],"y":[1]},"o":{"x":[0.167],"y":[0]},"t":85,"s":[100]},{"i":{"x":[0.833],"y":[1]},"o":{"x":[0.167],"y":[0]},"t":86,"s":[100]},{"i":{"x":[0.833],"y":[1]},"o":{"x":[0.167],"y":[0]},"t":87,"s":[100]},{"i":{"x":[0.833],"y":[1]},"o":{"x":[0.167],"y":[0]},"t":88,"s":[100]},{"i":{"x":[0.833],"y":[1]},"o":{"x":[0.167],"y":[0]},"t":89,"s":[100]},{"i":{"x":[0.833],"y":[1]},"o":{"x":[0.167],"y":[0]},"t":90,"s":[100]},{"i":{"x":[0.833],"y":[1]},"o":{"x":[0.167],"y":[0]},"t":91,"s":[100]},{"i":{"x":[0.833],"y":[1]},"o":{"x":[0.167],"y":[0]},"t":92,"s":[100]},{"i":{"x":[0.833],"y":[1]},"o":{"x":[0.167],"y":[0]},"t":93,"s":[100]},{"i":{"x":[0.833],"y":[1]},"o":{"x":[0.167],"y":[0]},"t":94,"s":[100]},{"i":{"x":[0.833],"y":[1]},"o":{"x":[0.167],"y":[0]},"t":95,"s":[100]},{"i":{"x":[0.833],"y":[1]},"o":{"x":[0.167],"y":[0]},"t":96,"s":[100]},{"i":{"x":[0.833],"y":[1]},"o":{"x":[0.167],"y":[0]},"t":97,"s":[100]},{"i":{"x":[0.833],"y":[1]},"o":{"x":[0.167],"y":[0]},"t":98,"s":[100]},{"i":{"x":[0.833],"y":[1]},"o":{"x":[0.167],"y":[0]},"t":99,"s":[100]},{"i":{"x":[0.833],"y":[1]},"o":{"x":[0.167],"y":[0]},"t":100,"s":[100]},{"i":{"x":[0.833],"y":[1]},"o":{"x":[0.167],"y":[0]},"t":101,"s":[100]},{"i":{"x":[0.833],"y":[1]},"o":{"x":[0.167],"y":[0]},"t":102,"s":[100]},{"i":{"x":[0.833],"y":[0.333]},"o":{"x":[0.167],"y":[0.083]},"t":103,"s":[100]},{"i":{"x":[0.833],"y":[0.69]},"o":{"x":[0.167],"y":[0.095]},"t":104,"s":[99.997]},{"i":{"x":[0.833],"y":[0.754]},"o":{"x":[0.167],"y":[0.114]},"t":105,"s":[99.98]},{"i":{"x":[0.833],"y":[0.779]},"o":{"x":[0.167],"y":[0.126]},"t":106,"s":[99.931]},{"i":{"x":[0.833],"y":[0.792]},"o":{"x":[0.167],"y":[0.134]},"t":107,"s":[99.837]},{"i":{"x":[0.833],"y":[0.8]},"o":{"x":[0.167],"y":[0.139]},"t":108,"s":[99.682]},{"i":{"x":[0.833],"y":[0.806]},"o":{"x":[0.167],"y":[0.143]},"t":109,"s":[99.45]},{"i":{"x":[0.833],"y":[0.81]},"o":{"x":[0.167],"y":[0.146]},"t":110,"s":[99.127]},{"i":{"x":[0.833],"y":[0.813]},"o":{"x":[0.167],"y":[0.148]},"t":111,"s":[98.697]},{"i":{"x":[0.833],"y":[0.815]},"o":{"x":[0.167],"y":[0.15]},"t":112,"s":[98.145]},{"i":{"x":[0.833],"y":[0.817]},"o":{"x":[0.167],"y":[0.152]},"t":113,"s":[97.456]},{"i":{"x":[0.833],"y":[0.818]},"o":{"x":[0.167],"y":[0.153]},"t":114,"s":[96.614]},{"i":{"x":[0.833],"y":[0.819]},"o":{"x":[0.167],"y":[0.154]},"t":115,"s":[95.604]},{"i":{"x":[0.833],"y":[0.821]},"o":{"x":[0.167],"y":[0.155]},"t":116,"s":[94.41]},{"i":{"x":[0.833],"y":[0.821]},"o":{"x":[0.167],"y":[0.156]},"t":117,"s":[93.019]},{"i":{"x":[0.833],"y":[0.822]},"o":{"x":[0.167],"y":[0.156]},"t":118,"s":[91.413]},{"i":{"x":[0.833],"y":[0.823]},"o":{"x":[0.167],"y":[0.157]},"t":119,"s":[89.579]},{"i":{"x":[0.833],"y":[0.824]},"o":{"x":[0.167],"y":[0.157]},"t":120,"s":[87.5]},{"i":{"x":[0.833],"y":[0.824]},"o":{"x":[0.167],"y":[0.158]},"t":121,"s":[85.162]},{"i":{"x":[0.833],"y":[0.825]},"o":{"x":[0.167],"y":[0.158]},"t":122,"s":[82.549]},{"i":{"x":[0.833],"y":[0.825]},"o":{"x":[0.167],"y":[0.159]},"t":123,"s":[79.646]},{"i":{"x":[0.833],"y":[0.825]},"o":{"x":[0.167],"y":[0.159]},"t":124,"s":[76.438]},{"i":{"x":[0.833],"y":[0.826]},"o":{"x":[0.167],"y":[0.159]},"t":125,"s":[72.909]},{"i":{"x":[0.833],"y":[0.826]},"o":{"x":[0.167],"y":[0.16]},"t":126,"s":[69.044]},{"i":{"x":[0.833],"y":[0.826]},"o":{"x":[0.167],"y":[0.16]},"t":127,"s":[64.828]},{"i":{"x":[0.833],"y":[0.827]},"o":{"x":[0.167],"y":[0.16]},"t":128,"s":[60.246]},{"i":{"x":[0.833],"y":[0.827]},"o":{"x":[0.167],"y":[0.16]},"t":129,"s":[55.282]},{"i":{"x":[0.833],"y":[0.827]},"o":{"x":[0.167],"y":[0.161]},"t":130,"s":[49.921]},{"i":{"x":[0.833],"y":[0.827]},"o":{"x":[0.167],"y":[0.161]},"t":131,"s":[44.148]},{"i":{"x":[0.833],"y":[0.828]},"o":{"x":[0.167],"y":[0.161]},"t":132,"s":[37.948]},{"i":{"x":[0.833],"y":[0.828]},"o":{"x":[0.167],"y":[0.161]},"t":133,"s":[31.305]},{"i":{"x":[0.833],"y":[0.828]},"o":{"x":[0.167],"y":[0.161]},"t":134,"s":[24.204]},{"i":{"x":[0.833],"y":[0.828]},"o":{"x":[0.167],"y":[0.162]},"t":135,"s":[16.629]},{"i":{"x":[0.833],"y":[0.833]},"o":{"x":[0.167],"y":[0.162]},"t":136,"s":[8.567]},{"t":137.000005580124,"s":[0]}],"ix":11},"r":{"a":0,"k":0,"ix":10},"p":{"a":0,"k":[704,280,0],"ix":2},"a":{"a":0,"k":[91,52.5,0],"ix":1},"s":{"a":0,"k":[160.952,160.952,100],"ix":6}},"ao":0,"shapes":[{"ty":"gr","it":[{"ind":0,"ty":"sh","ix":1,"ks":{"a":0,"k":{"i":[[0,0.039],[0.596,0.592],[0,0],[0.387,0.158],[0.417,-0.001],[0,0],[0.398,-0.173],[0.295,-0.315],[0.148,-0.409],[-0.029,-0.432],[-11.798,-16.39],[-18.728,-7.774],[-20.048,3.171],[-15.361,13.166],[-0.189,0.392],[-0.015,0.435]],"o":[[-0.004,-0.838],[0,0],[-0.295,-0.293],[-0.386,-0.157],[0,0],[-0.435,-0.001],[-0.398,0.172],[-0.299,0.318],[-0.147,0.408],[1.336,20.097],[11.799,16.391],[18.728,7.774],[20.047,-3.17],[0.334,-0.285],[0.19,-0.392],[0.004,-0.039]],"v":[[90.693,23.652],[89.756,21.42],[15.943,-51.471],[14.91,-52.154],[13.693,-52.39],[-87.517,-52.16],[-88.78,-51.9],[-89.831,-51.161],[-90.508,-50.06],[-90.687,-48.785],[-70.595,7.031],[-23.896,43.997],[35.422,51.039],[89.589,26.049],[90.378,25.023],[90.689,23.769]],"c":true},"ix":2},"nm":"Path 1","mn":"ADBE Vector Shape - Group","hd":false},{"ty":"fl","c":{"a":0,"k":[0.848966172162,0.911711748909,0.951250741996,1],"ix":4},"o":{"a":0,"k":100,"ix":5},"r":1,"bm":0,"nm":"Fill 1","mn":"ADBE Vector Graphic - Fill","hd":false},{"ty":"tr","p":{"a":0,"k":[90.693,52.39],"ix":2},"a":{"a":0,"k":[0,0],"ix":1},"s":{"a":0,"k":[100,100],"ix":3},"r":{"a":0,"k":0,"ix":6},"o":{"a":0,"k":100,"ix":7},"sk":{"a":0,"k":0,"ix":4},"sa":{"a":0,"k":0,"ix":5},"nm":"Transform"}],"nm":"Group 1","np":4,"cix":2,"bm":0,"ix":1,"mn":"ADBE Vector Group","hd":false}],"ip":12.00000048877,"op":138.000005620855,"st":-53.0000021587343,"bm":0},{"ddd":0,"ind":4,"ty":4,"nm":"REctangle","td":1,"sr":1,"ks":{"o":{"a":0,"k":100,"ix":11},"r":{"a":0,"k":0,"ix":10},"p":{"a":1,"k":[{"i":{"x":0.598,"y":0.264},"o":{"x":0.167,"y":0.167},"t":-26,"s":[1830,621,0],"to":[0,-79.997,0],"ti":[0,157.185,0]},{"i":{"x":0.697,"y":1},"o":{"x":0.352,"y":0.146},"t":0,"s":[1830,712.154,0],"to":[0,-39.631,0],"ti":[0,20.17,0]},{"t":20.0000008146167,"s":[1830,20,0]}],"ix":2},"a":{"a":0,"k":[0,0,0],"ix":1},"s":{"a":0,"k":[182.061,196.872,100],"ix":6}},"ao":0,"shapes":[{"ty":"gr","it":[{"ty":"rc","d":1,"s":{"a":0,"k":[260.797,283.016],"ix":2},"p":{"a":0,"k":[0,0],"ix":3},"r":{"a":0,"k":0,"ix":4},"nm":"Rectangle Path 1","mn":"ADBE Vector Shape - Rect","hd":false},{"ty":"st","c":{"a":0,"k":[1,1,1,1],"ix":3},"o":{"a":0,"k":100,"ix":4},"w":{"a":0,"k":2,"ix":5},"lc":1,"lj":1,"ml":4,"bm":0,"nm":"Stroke 1","mn":"ADBE Vector Graphic - Stroke","hd":false},{"ty":"fl","c":{"a":0,"k":[0,0.305881993911,0.439215985466,1],"ix":4},"o":{"a":0,"k":100,"ix":5},"r":1,"bm":0,"nm":"Fill 1","mn":"ADBE Vector Graphic - Fill","hd":false},{"ty":"tr","p":{"a":0,"k":[-721.602,400.508],"ix":2},"a":{"a":0,"k":[0,0],"ix":1},"s":{"a":0,"k":[249.061,117.215],"ix":3},"r":{"a":0,"k":0,"ix":6},"o":{"a":0,"k":100,"ix":7},"sk":{"a":0,"k":0,"ix":4},"sa":{"a":0,"k":0,"ix":5},"nm":"Transform"}],"nm":"Rectangle 1","np":3,"cix":2,"bm":0,"ix":1,"mn":"ADBE Vector Group","hd":false}],"ip":-26.0000010590017,"op":139.000005661586,"st":-26.0000010590017,"bm":0},{"ddd":0,"ind":5,"ty":0,"nm":"Pre-comp 3","tt":1,"refId":"comp_1","sr":1,"ks":{"o":{"a":0,"k":100,"ix":11},"r":{"a":0,"k":0,"ix":10},"p":{"a":0,"k":[960,541,0],"ix":2},"a":{"a":0,"k":[960,541,0],"ix":1},"s":{"a":0,"k":[100,100,100],"ix":6}},"ao":0,"w":1920,"h":1082,"ip":-3.00000012219251,"op":140.000005702317,"st":-3.00000012219251,"bm":0},{"ddd":0,"ind":6,"ty":4,"nm":"Cuadrado 1","sr":1,"ks":{"o":{"a":1,"k":[{"i":{"x":[0.833],"y":[0.843]},"o":{"x":[0.167],"y":[0.167]},"t":1,"s":[0]},{"i":{"x":[0.833],"y":[0.844]},"o":{"x":[0.167],"y":[0.178]},"t":2,"s":[16.629]},{"i":{"x":[0.833],"y":[0.844]},"o":{"x":[0.167],"y":[0.179]},"t":3,"s":[31.305]},{"i":{"x":[0.833],"y":[0.845]},"o":{"x":[0.167],"y":[0.179]},"t":4,"s":[44.148]},{"i":{"x":[0.833],"y":[0.846]},"o":{"x":[0.167],"y":[0.181]},"t":5,"s":[55.282]},{"i":{"x":[0.833],"y":[0.847]},"o":{"x":[0.167],"y":[0.182]},"t":6,"s":[64.828]},{"i":{"x":[0.833],"y":[0.848]},"o":{"x":[0.167],"y":[0.183]},"t":7,"s":[72.909]},{"i":{"x":[0.833],"y":[0.85]},"o":{"x":[0.167],"y":[0.185]},"t":8,"s":[79.646]},{"i":{"x":[0.833],"y":[0.852]},"o":{"x":[0.167],"y":[0.187]},"t":9,"s":[85.162]},{"i":{"x":[0.833],"y":[0.854]},"o":{"x":[0.167],"y":[0.19]},"t":10,"s":[89.579]},{"i":{"x":[0.833],"y":[0.857]},"o":{"x":[0.167],"y":[0.194]},"t":11,"s":[93.019]},{"i":{"x":[0.833],"y":[0.861]},"o":{"x":[0.167],"y":[0.2]},"t":12,"s":[95.604]},{"i":{"x":[0.833],"y":[0.866]},"o":{"x":[0.167],"y":[0.208]},"t":13,"s":[97.456]},{"i":{"x":[0.833],"y":[0.874]},"o":{"x":[0.167],"y":[0.221]},"t":14,"s":[98.697]},{"i":{"x":[0.833],"y":[0.886]},"o":{"x":[0.167],"y":[0.246]},"t":15,"s":[99.45]},{"i":{"x":[0.833],"y":[0.905]},"o":{"x":[0.167],"y":[0.31]},"t":16,"s":[99.837]},{"i":{"x":[0.833],"y":[0.917]},"o":{"x":[0.167],"y":[0.667]},"t":17,"s":[99.98]},{"i":{"x":[0.833],"y":[1]},"o":{"x":[0.167],"y":[0.002]},"t":18,"s":[100]},{"i":{"x":[0.833],"y":[1]},"o":{"x":[0.167],"y":[0]},"t":19,"s":[100]},{"i":{"x":[0.833],"y":[1]},"o":{"x":[0.167],"y":[0]},"t":20,"s":[100]},{"i":{"x":[0.833],"y":[1]},"o":{"x":[0.167],"y":[0]},"t":21,"s":[100]},{"i":{"x":[0.833],"y":[1]},"o":{"x":[0.167],"y":[0]},"t":22,"s":[100]},{"i":{"x":[0.833],"y":[1]},"o":{"x":[0.167],"y":[0]},"t":23,"s":[100]},{"i":{"x":[0.833],"y":[1]},"o":{"x":[0.167],"y":[0]},"t":24,"s":[100]},{"i":{"x":[0.833],"y":[1]},"o":{"x":[0.167],"y":[0]},"t":25,"s":[100]},{"i":{"x":[0.833],"y":[1]},"o":{"x":[0.167],"y":[0]},"t":26,"s":[100]},{"i":{"x":[0.833],"y":[1]},"o":{"x":[0.167],"y":[0]},"t":27,"s":[100]},{"i":{"x":[0.833],"y":[1]},"o":{"x":[0.167],"y":[0]},"t":28,"s":[100]},{"i":{"x":[0.833],"y":[1]},"o":{"x":[0.167],"y":[0]},"t":29,"s":[100]},{"i":{"x":[0.833],"y":[1]},"o":{"x":[0.167],"y":[0]},"t":30,"s":[100]},{"i":{"x":[0.833],"y":[1]},"o":{"x":[0.167],"y":[0]},"t":31,"s":[100]},{"i":{"x":[0.833],"y":[1]},"o":{"x":[0.167],"y":[0]},"t":32,"s":[100]},{"i":{"x":[0.833],"y":[1]},"o":{"x":[0.167],"y":[0]},"t":33,"s":[100]},{"i":{"x":[0.833],"y":[1]},"o":{"x":[0.167],"y":[0]},"t":34,"s":[100]},{"i":{"x":[0.833],"y":[1]},"o":{"x":[0.167],"y":[0]},"t":35,"s":[100]},{"i":{"x":[0.833],"y":[1]},"o":{"x":[0.167],"y":[0]},"t":36,"s":[100]},{"i":{"x":[0.833],"y":[1]},"o":{"x":[0.167],"y":[0]},"t":37,"s":[100]},{"i":{"x":[0.833],"y":[1]},"o":{"x":[0.167],"y":[0]},"t":38,"s":[100]},{"i":{"x":[0.833],"y":[1]},"o":{"x":[0.167],"y":[0]},"t":39,"s":[100]},{"i":{"x":[0.833],"y":[1]},"o":{"x":[0.167],"y":[0]},"t":40,"s":[100]},{"i":{"x":[0.833],"y":[1]},"o":{"x":[0.167],"y":[0]},"t":41,"s":[100]},{"i":{"x":[0.833],"y":[1]},"o":{"x":[0.167],"y":[0]},"t":42,"s":[100]},{"i":{"x":[0.833],"y":[1]},"o":{"x":[0.167],"y":[0]},"t":43,"s":[100]},{"i":{"x":[0.833],"y":[1]},"o":{"x":[0.167],"y":[0]},"t":44,"s":[100]},{"i":{"x":[0.833],"y":[1]},"o":{"x":[0.167],"y":[0]},"t":45,"s":[100]},{"i":{"x":[0.833],"y":[1]},"o":{"x":[0.167],"y":[0]},"t":46,"s":[100]},{"i":{"x":[0.833],"y":[1]},"o":{"x":[0.167],"y":[0]},"t":47,"s":[100]},{"i":{"x":[0.833],"y":[1]},"o":{"x":[0.167],"y":[0]},"t":48,"s":[100]},{"i":{"x":[0.833],"y":[1]},"o":{"x":[0.167],"y":[0]},"t":49,"s":[100]},{"i":{"x":[0.833],"y":[1]},"o":{"x":[0.167],"y":[0]},"t":50,"s":[100]},{"i":{"x":[0.833],"y":[1]},"o":{"x":[0.167],"y":[0]},"t":51,"s":[100]},{"i":{"x":[0.833],"y":[1]},"o":{"x":[0.167],"y":[0]},"t":52,"s":[100]},{"i":{"x":[0.833],"y":[1]},"o":{"x":[0.167],"y":[0]},"t":53,"s":[100]},{"i":{"x":[0.833],"y":[1]},"o":{"x":[0.167],"y":[0]},"t":54,"s":[100]},{"i":{"x":[0.833],"y":[1]},"o":{"x":[0.167],"y":[0]},"t":55,"s":[100]},{"i":{"x":[0.833],"y":[1]},"o":{"x":[0.167],"y":[0]},"t":56,"s":[100]},{"i":{"x":[0.833],"y":[1]},"o":{"x":[0.167],"y":[0]},"t":57,"s":[100]},{"i":{"x":[0.833],"y":[1]},"o":{"x":[0.167],"y":[0]},"t":58,"s":[100]},{"i":{"x":[0.833],"y":[1]},"o":{"x":[0.167],"y":[0]},"t":59,"s":[100]},{"i":{"x":[0.833],"y":[1]},"o":{"x":[0.167],"y":[0]},"t":60,"s":[100]},{"i":{"x":[0.833],"y":[1]},"o":{"x":[0.167],"y":[0]},"t":61,"s":[100]},{"i":{"x":[0.833],"y":[1]},"o":{"x":[0.167],"y":[0]},"t":62,"s":[100]},{"i":{"x":[0.833],"y":[1]},"o":{"x":[0.167],"y":[0]},"t":63,"s":[100]},{"i":{"x":[0.833],"y":[1]},"o":{"x":[0.167],"y":[0]},"t":64,"s":[100]},{"i":{"x":[0.833],"y":[1]},"o":{"x":[0.167],"y":[0]},"t":65,"s":[100]},{"i":{"x":[0.833],"y":[1]},"o":{"x":[0.167],"y":[0]},"t":66,"s":[100]},{"i":{"x":[0.833],"y":[1]},"o":{"x":[0.167],"y":[0]},"t":67,"s":[100]},{"i":{"x":[0.833],"y":[1]},"o":{"x":[0.167],"y":[0]},"t":68,"s":[100]},{"i":{"x":[0.833],"y":[1]},"o":{"x":[0.167],"y":[0]},"t":69,"s":[100]},{"i":{"x":[0.833],"y":[1]},"o":{"x":[0.167],"y":[0]},"t":70,"s":[100]},{"i":{"x":[0.833],"y":[1]},"o":{"x":[0.167],"y":[0]},"t":71,"s":[100]},{"i":{"x":[0.833],"y":[1]},"o":{"x":[0.167],"y":[0]},"t":72,"s":[100]},{"i":{"x":[0.833],"y":[1]},"o":{"x":[0.167],"y":[0]},"t":73,"s":[100]},{"i":{"x":[0.833],"y":[1]},"o":{"x":[0.167],"y":[0]},"t":74,"s":[100]},{"i":{"x":[0.833],"y":[1]},"o":{"x":[0.167],"y":[0]},"t":75,"s":[100]},{"i":{"x":[0.833],"y":[1]},"o":{"x":[0.167],"y":[0]},"t":76,"s":[100]},{"i":{"x":[0.833],"y":[1]},"o":{"x":[0.167],"y":[0]},"t":77,"s":[100]},{"i":{"x":[0.833],"y":[1]},"o":{"x":[0.167],"y":[0]},"t":78,"s":[100]},{"i":{"x":[0.833],"y":[1]},"o":{"x":[0.167],"y":[0]},"t":79,"s":[100]},{"i":{"x":[0.833],"y":[1]},"o":{"x":[0.167],"y":[0]},"t":80,"s":[100]},{"i":{"x":[0.833],"y":[1]},"o":{"x":[0.167],"y":[0]},"t":81,"s":[100]},{"i":{"x":[0.833],"y":[1]},"o":{"x":[0.167],"y":[0]},"t":82,"s":[100]},{"i":{"x":[0.833],"y":[1]},"o":{"x":[0.167],"y":[0]},"t":83,"s":[100]},{"i":{"x":[0.833],"y":[1]},"o":{"x":[0.167],"y":[0]},"t":84,"s":[100]},{"i":{"x":[0.833],"y":[1]},"o":{"x":[0.167],"y":[0]},"t":85,"s":[100]},{"i":{"x":[0.833],"y":[1]},"o":{"x":[0.167],"y":[0]},"t":86,"s":[100]},{"i":{"x":[0.833],"y":[1]},"o":{"x":[0.167],"y":[0]},"t":87,"s":[100]},{"i":{"x":[0.833],"y":[1]},"o":{"x":[0.167],"y":[0]},"t":88,"s":[100]},{"i":{"x":[0.833],"y":[1]},"o":{"x":[0.167],"y":[0]},"t":89,"s":[100]},{"i":{"x":[0.833],"y":[1]},"o":{"x":[0.167],"y":[0]},"t":90,"s":[100]},{"i":{"x":[0.833],"y":[1]},"o":{"x":[0.167],"y":[0]},"t":91,"s":[100]},{"i":{"x":[0.833],"y":[1.011]},"o":{"x":[0.167],"y":[0]},"t":92,"s":[100]},{"i":{"x":[0.833],"y":[0.333]},"o":{"x":[0.167],"y":[0.083]},"t":93,"s":[100]},{"i":{"x":[0.833],"y":[0.69]},"o":{"x":[0.167],"y":[0.095]},"t":94,"s":[99.863]},{"i":{"x":[0.833],"y":[0.754]},"o":{"x":[0.167],"y":[0.114]},"t":95,"s":[98.903]},{"i":{"x":[0.833],"y":[0.779]},"o":{"x":[0.167],"y":[0.126]},"t":96,"s":[96.296]},{"i":{"x":[0.833],"y":[0.792]},"o":{"x":[0.167],"y":[0.134]},"t":97,"s":[91.221]},{"i":{"x":[0.833],"y":[0.8]},"o":{"x":[0.167],"y":[0.139]},"t":98,"s":[82.853]},{"i":{"x":[0.833],"y":[0.806]},"o":{"x":[0.167],"y":[0.143]},"t":99,"s":[70.37]},{"i":{"x":[0.833],"y":[0.81]},"o":{"x":[0.167],"y":[0.146]},"t":100,"s":[52.949]},{"i":{"x":[0.833],"y":[0.833]},"o":{"x":[0.167],"y":[0.148]},"t":101,"s":[29.767]},{"t":102.000004154545,"s":[0]}],"ix":11},"r":{"a":0,"k":0,"ix":10},"p":{"a":0,"k":[500,620,0],"ix":2},"a":{"a":0,"k":[136,89,0],"ix":1},"s":{"a":0,"k":[171.91,171.91,100],"ix":6}},"ao":0,"shapes":[{"ty":"gr","it":[{"ind":0,"ty":"sh","ix":1,"ks":{"a":0,"k":{"i":[[0,0],[0,0],[0,0],[0,0]],"o":[[0,0],[0,0],[0,0],[0,0]],"v":[[-135.742,88.661],[135.742,88.661],[135.742,-88.661],[-135.742,-88.661]],"c":true},"ix":2},"nm":"Path 1","mn":"ADBE Vector Shape - Group","hd":false},{"ind":1,"ty":"sh","ix":2,"ks":{"a":0,"k":{"i":[[0,0]],"o":[[0,0]],"v":[[-135.742,-88.661]],"c":false},"ix":2},"nm":"Path 2","mn":"ADBE Vector Shape - Group","hd":false},{"ind":2,"ty":"sh","ix":3,"ks":{"a":0,"k":{"i":[[0,0],[0,0],[0,0],[0,0]],"o":[[0,0],[0,0],[0,0],[0,0]],"v":[[-120.58,-73.497],[120.578,-73.497],[120.578,73.496],[-120.58,73.496]],"c":true},"ix":2},"nm":"Path 3","mn":"ADBE Vector Shape - Group","hd":false},{"ty":"mm","mm":1,"nm":"Merge Paths 1","mn":"ADBE Vector Filter - Merge","hd":false},{"ty":"fl","c":{"a":0,"k":[0.139809686997,0.407291098202,0.536257455863,1],"ix":4},"o":{"a":0,"k":100,"ix":5},"r":1,"bm":0,"nm":"Fill 1","mn":"ADBE Vector Graphic - Fill","hd":false},{"ty":"tr","p":{"a":0,"k":[135.742,88.661],"ix":2},"a":{"a":0,"k":[0,0],"ix":1},"s":{"a":0,"k":[100,100],"ix":3},"r":{"a":0,"k":0,"ix":6},"o":{"a":0,"k":100,"ix":7},"sk":{"a":0,"k":0,"ix":4},"sa":{"a":0,"k":0,"ix":5},"nm":"Transform"}],"nm":"Group 1","np":5,"cix":2,"bm":0,"ix":1,"mn":"ADBE Vector Group","hd":false}],"ip":1.00000004073083,"op":103.000004195276,"st":1.00000004073083,"bm":0},{"ddd":0,"ind":8,"ty":4,"nm":"Big Pie chart yellow","sr":1,"ks":{"o":{"a":1,"k":[{"i":{"x":[0.833],"y":[0.837]},"o":{"x":[0.167],"y":[0.167]},"t":12,"s":[0]},{"i":{"x":[0.833],"y":[0.838]},"o":{"x":[0.167],"y":[0.171]},"t":13,"s":[7.314]},{"i":{"x":[0.833],"y":[0.838]},"o":{"x":[0.167],"y":[0.171]},"t":14,"s":[14.263]},{"i":{"x":[0.833],"y":[0.838]},"o":{"x":[0.167],"y":[0.171]},"t":15,"s":[20.855]},{"i":{"x":[0.833],"y":[0.838]},"o":{"x":[0.167],"y":[0.171]},"t":16,"s":[27.1]},{"i":{"x":[0.833],"y":[0.838]},"o":{"x":[0.167],"y":[0.172]},"t":17,"s":[33.008]},{"i":{"x":[0.833],"y":[0.838]},"o":{"x":[0.167],"y":[0.172]},"t":18,"s":[38.588]},{"i":{"x":[0.833],"y":[0.838]},"o":{"x":[0.167],"y":[0.172]},"t":19,"s":[43.848]},{"i":{"x":[0.833],"y":[0.839]},"o":{"x":[0.167],"y":[0.172]},"t":20,"s":[48.8]},{"i":{"x":[0.833],"y":[0.839]},"o":{"x":[0.167],"y":[0.172]},"t":21,"s":[53.452]},{"i":{"x":[0.833],"y":[0.839]},"o":{"x":[0.167],"y":[0.172]},"t":22,"s":[57.812]},{"i":{"x":[0.833],"y":[0.839]},"o":{"x":[0.167],"y":[0.173]},"t":23,"s":[61.892]},{"i":{"x":[0.833],"y":[0.839]},"o":{"x":[0.167],"y":[0.173]},"t":24,"s":[65.7]},{"i":{"x":[0.833],"y":[0.84]},"o":{"x":[0.167],"y":[0.173]},"t":25,"s":[69.245]},{"i":{"x":[0.833],"y":[0.84]},"o":{"x":[0.167],"y":[0.173]},"t":26,"s":[72.537]},{"i":{"x":[0.833],"y":[0.84]},"o":{"x":[0.167],"y":[0.174]},"t":27,"s":[75.586]},{"i":{"x":[0.833],"y":[0.84]},"o":{"x":[0.167],"y":[0.174]},"t":28,"s":[78.4]},{"i":{"x":[0.833],"y":[0.841]},"o":{"x":[0.167],"y":[0.174]},"t":29,"s":[80.989]},{"i":{"x":[0.833],"y":[0.841]},"o":{"x":[0.167],"y":[0.175]},"t":30,"s":[83.362]},{"i":{"x":[0.833],"y":[0.841]},"o":{"x":[0.167],"y":[0.175]},"t":31,"s":[85.53]},{"i":{"x":[0.833],"y":[0.842]},"o":{"x":[0.167],"y":[0.175]},"t":32,"s":[87.5]},{"i":{"x":[0.833],"y":[0.842]},"o":{"x":[0.167],"y":[0.176]},"t":33,"s":[89.283]},{"i":{"x":[0.833],"y":[0.843]},"o":{"x":[0.167],"y":[0.176]},"t":34,"s":[90.888]},{"i":{"x":[0.833],"y":[0.843]},"o":{"x":[0.167],"y":[0.177]},"t":35,"s":[92.323]},{"i":{"x":[0.833],"y":[0.844]},"o":{"x":[0.167],"y":[0.178]},"t":36,"s":[93.6]},{"i":{"x":[0.833],"y":[0.844]},"o":{"x":[0.167],"y":[0.179]},"t":37,"s":[94.727]},{"i":{"x":[0.833],"y":[0.845]},"o":{"x":[0.167],"y":[0.179]},"t":38,"s":[95.713]},{"i":{"x":[0.833],"y":[0.846]},"o":{"x":[0.167],"y":[0.181]},"t":39,"s":[96.567]},{"i":{"x":[0.833],"y":[0.847]},"o":{"x":[0.167],"y":[0.182]},"t":40,"s":[97.3]},{"i":{"x":[0.833],"y":[0.848]},"o":{"x":[0.167],"y":[0.183]},"t":41,"s":[97.92]},{"i":{"x":[0.833],"y":[0.85]},"o":{"x":[0.167],"y":[0.185]},"t":42,"s":[98.438]},{"i":{"x":[0.833],"y":[0.852]},"o":{"x":[0.167],"y":[0.187]},"t":43,"s":[98.861]},{"i":{"x":[0.833],"y":[0.854]},"o":{"x":[0.167],"y":[0.19]},"t":44,"s":[99.2]},{"i":{"x":[0.833],"y":[0.857]},"o":{"x":[0.167],"y":[0.194]},"t":45,"s":[99.464]},{"i":{"x":[0.833],"y":[0.861]},"o":{"x":[0.167],"y":[0.2]},"t":46,"s":[99.662]},{"i":{"x":[0.833],"y":[0.866]},"o":{"x":[0.167],"y":[0.208]},"t":47,"s":[99.805]},{"i":{"x":[0.833],"y":[0.874]},"o":{"x":[0.167],"y":[0.221]},"t":48,"s":[99.9]},{"i":{"x":[0.833],"y":[0.886]},"o":{"x":[0.167],"y":[0.246]},"t":49,"s":[99.958]},{"i":{"x":[0.833],"y":[0.905]},"o":{"x":[0.167],"y":[0.31]},"t":50,"s":[99.987]},{"i":{"x":[0.833],"y":[0.917]},"o":{"x":[0.167],"y":[0.667]},"t":51,"s":[99.998]},{"i":{"x":[0.833],"y":[1]},"o":{"x":[0.167],"y":[0]},"t":52,"s":[100]},{"i":{"x":[0.833],"y":[1]},"o":{"x":[0.167],"y":[0]},"t":53,"s":[100]},{"i":{"x":[0.833],"y":[1]},"o":{"x":[0.167],"y":[0]},"t":54,"s":[100]},{"i":{"x":[0.833],"y":[1]},"o":{"x":[0.167],"y":[0]},"t":55,"s":[100]},{"i":{"x":[0.833],"y":[1]},"o":{"x":[0.167],"y":[0]},"t":56,"s":[100]},{"i":{"x":[0.833],"y":[1]},"o":{"x":[0.167],"y":[0]},"t":57,"s":[100]},{"i":{"x":[0.833],"y":[1]},"o":{"x":[0.167],"y":[0]},"t":58,"s":[100]},{"i":{"x":[0.833],"y":[1]},"o":{"x":[0.167],"y":[0]},"t":59,"s":[100]},{"i":{"x":[0.833],"y":[1]},"o":{"x":[0.167],"y":[0]},"t":60,"s":[100]},{"i":{"x":[0.833],"y":[1]},"o":{"x":[0.167],"y":[0]},"t":61,"s":[100]},{"i":{"x":[0.833],"y":[1]},"o":{"x":[0.167],"y":[0]},"t":62,"s":[100]},{"i":{"x":[0.833],"y":[1]},"o":{"x":[0.167],"y":[0]},"t":63,"s":[100]},{"i":{"x":[0.833],"y":[1]},"o":{"x":[0.167],"y":[0]},"t":64,"s":[100]},{"i":{"x":[0.833],"y":[1]},"o":{"x":[0.167],"y":[0]},"t":65,"s":[100]},{"i":{"x":[0.833],"y":[1]},"o":{"x":[0.167],"y":[0]},"t":66,"s":[100]},{"i":{"x":[0.833],"y":[1]},"o":{"x":[0.167],"y":[0]},"t":67,"s":[100]},{"i":{"x":[0.833],"y":[1]},"o":{"x":[0.167],"y":[0]},"t":68,"s":[100]},{"i":{"x":[0.833],"y":[1]},"o":{"x":[0.167],"y":[0]},"t":69,"s":[100]},{"i":{"x":[0.833],"y":[1]},"o":{"x":[0.167],"y":[0]},"t":70,"s":[100]},{"i":{"x":[0.833],"y":[1]},"o":{"x":[0.167],"y":[0]},"t":71,"s":[100]},{"i":{"x":[0.833],"y":[1]},"o":{"x":[0.167],"y":[0]},"t":72,"s":[100]},{"i":{"x":[0.833],"y":[1]},"o":{"x":[0.167],"y":[0]},"t":73,"s":[100]},{"i":{"x":[0.833],"y":[1]},"o":{"x":[0.167],"y":[0]},"t":74,"s":[100]},{"i":{"x":[0.833],"y":[1]},"o":{"x":[0.167],"y":[0]},"t":75,"s":[100]},{"i":{"x":[0.833],"y":[1]},"o":{"x":[0.167],"y":[0]},"t":76,"s":[100]},{"i":{"x":[0.833],"y":[1]},"o":{"x":[0.167],"y":[0]},"t":77,"s":[100]},{"i":{"x":[0.833],"y":[1]},"o":{"x":[0.167],"y":[0]},"t":78,"s":[100]},{"i":{"x":[0.833],"y":[1]},"o":{"x":[0.167],"y":[0]},"t":79,"s":[100]},{"i":{"x":[0.833],"y":[1]},"o":{"x":[0.167],"y":[0]},"t":80,"s":[100]},{"i":{"x":[0.833],"y":[1]},"o":{"x":[0.167],"y":[0]},"t":81,"s":[100]},{"i":{"x":[0.833],"y":[1]},"o":{"x":[0.167],"y":[0]},"t":82,"s":[100]},{"i":{"x":[0.833],"y":[1]},"o":{"x":[0.167],"y":[0]},"t":83,"s":[100]},{"i":{"x":[0.833],"y":[1]},"o":{"x":[0.167],"y":[0]},"t":84,"s":[100]},{"i":{"x":[0.833],"y":[1]},"o":{"x":[0.167],"y":[0]},"t":85,"s":[100]},{"i":{"x":[0.833],"y":[1]},"o":{"x":[0.167],"y":[0]},"t":86,"s":[100]},{"i":{"x":[0.833],"y":[1]},"o":{"x":[0.167],"y":[0]},"t":87,"s":[100]},{"i":{"x":[0.833],"y":[1]},"o":{"x":[0.167],"y":[0]},"t":88,"s":[100]},{"i":{"x":[0.833],"y":[1]},"o":{"x":[0.167],"y":[0]},"t":89,"s":[100]},{"i":{"x":[0.833],"y":[1]},"o":{"x":[0.167],"y":[0]},"t":90,"s":[100]},{"i":{"x":[0.833],"y":[1]},"o":{"x":[0.167],"y":[0]},"t":91,"s":[100]},{"i":{"x":[0.833],"y":[1]},"o":{"x":[0.167],"y":[0]},"t":92,"s":[100]},{"i":{"x":[0.833],"y":[1]},"o":{"x":[0.167],"y":[0]},"t":93,"s":[100]},{"i":{"x":[0.833],"y":[1]},"o":{"x":[0.167],"y":[0]},"t":94,"s":[100]},{"i":{"x":[0.833],"y":[1]},"o":{"x":[0.167],"y":[0]},"t":95,"s":[100]},{"i":{"x":[0.833],"y":[1]},"o":{"x":[0.167],"y":[0]},"t":96,"s":[100]},{"i":{"x":[0.833],"y":[1]},"o":{"x":[0.167],"y":[0]},"t":97,"s":[100]},{"i":{"x":[0.833],"y":[1]},"o":{"x":[0.167],"y":[0]},"t":98,"s":[100]},{"i":{"x":[0.833],"y":[1]},"o":{"x":[0.167],"y":[0]},"t":99,"s":[100]},{"i":{"x":[0.833],"y":[1]},"o":{"x":[0.167],"y":[0]},"t":100,"s":[100]},{"i":{"x":[0.833],"y":[1]},"o":{"x":[0.167],"y":[0]},"t":101,"s":[100]},{"i":{"x":[0.833],"y":[1]},"o":{"x":[0.167],"y":[0]},"t":102,"s":[100]},{"i":{"x":[0.833],"y":[1]},"o":{"x":[0.167],"y":[0]},"t":103,"s":[100]},{"i":{"x":[0.833],"y":[1.003]},"o":{"x":[0.167],"y":[0]},"t":104,"s":[100]},{"i":{"x":[0.833],"y":[0.333]},"o":{"x":[0.167],"y":[0.083]},"t":105,"s":[100]},{"i":{"x":[0.833],"y":[0.69]},"o":{"x":[0.167],"y":[0.095]},"t":106,"s":[99.964]},{"i":{"x":[0.833],"y":[0.754]},"o":{"x":[0.167],"y":[0.114]},"t":107,"s":[99.708]},{"i":{"x":[0.833],"y":[0.779]},"o":{"x":[0.167],"y":[0.126]},"t":108,"s":[99.016]},{"i":{"x":[0.833],"y":[0.792]},"o":{"x":[0.167],"y":[0.134]},"t":109,"s":[97.668]},{"i":{"x":[0.833],"y":[0.8]},"o":{"x":[0.167],"y":[0.139]},"t":110,"s":[95.445]},{"i":{"x":[0.833],"y":[0.806]},"o":{"x":[0.167],"y":[0.143]},"t":111,"s":[92.128]},{"i":{"x":[0.833],"y":[0.81]},"o":{"x":[0.167],"y":[0.146]},"t":112,"s":[87.5]},{"i":{"x":[0.833],"y":[0.813]},"o":{"x":[0.167],"y":[0.148]},"t":113,"s":[81.341]},{"i":{"x":[0.833],"y":[0.815]},"o":{"x":[0.167],"y":[0.15]},"t":114,"s":[73.433]},{"i":{"x":[0.833],"y":[0.817]},"o":{"x":[0.167],"y":[0.152]},"t":115,"s":[63.557]},{"i":{"x":[0.833],"y":[0.818]},"o":{"x":[0.167],"y":[0.153]},"t":116,"s":[51.494]},{"i":{"x":[0.833],"y":[0.819]},"o":{"x":[0.167],"y":[0.154]},"t":117,"s":[37.026]},{"i":{"x":[0.833],"y":[0.833]},"o":{"x":[0.167],"y":[0.155]},"t":118,"s":[19.934]},{"t":119.000004846969,"s":[0]}],"ix":11},"r":{"a":0,"k":0,"ix":10},"p":{"a":1,"k":[{"i":{"x":0.571,"y":1},"o":{"x":0.525,"y":0.455},"t":13,"s":[1408,584,0],"to":[12,-18,0],"ti":[-12,18,0]},{"t":33.7212513734947,"s":[1480,476,0]}],"ix":2},"a":{"a":0,"k":[128,142,0],"ix":1},"s":{"a":0,"k":[159.375,159.375,100],"ix":6}},"ao":0,"shapes":[{"ty":"gr","it":[{"ind":0,"ty":"sh","ix":1,"ks":{"a":0,"k":{"i":[[0,0]],"o":[[0,0]],"v":[[-1581.177,-437.765]],"c":false},"ix":2},"nm":"Path 1","mn":"ADBE Vector Shape - Group","hd":false},{"ty":"st","c":{"a":0,"k":[1,1,1,1],"ix":3},"o":{"a":0,"k":100,"ix":4},"w":{"a":0,"k":2,"ix":5},"lc":1,"lj":1,"ml":4,"bm":0,"nm":"Stroke 1","mn":"ADBE Vector Graphic - Stroke","hd":false},{"ty":"fl","c":{"a":0,"k":[0.974557674632,0.831324797986,0.178477478027,1],"ix":4},"o":{"a":0,"k":100,"ix":5},"r":1,"bm":0,"nm":"Fill 1","mn":"ADBE Vector Graphic - Fill","hd":false},{"ty":"tr","p":{"a":0,"k":[0,0],"ix":2},"a":{"a":0,"k":[0,0],"ix":1},"s":{"a":0,"k":[100,100],"ix":3},"r":{"a":0,"k":0,"ix":6},"o":{"a":0,"k":100,"ix":7},"sk":{"a":0,"k":0,"ix":4},"sa":{"a":0,"k":0,"ix":5},"nm":"Transform"}],"nm":"Shape 1","np":3,"cix":2,"bm":0,"ix":1,"mn":"ADBE Vector Group","hd":false},{"ty":"gr","it":[{"ind":0,"ty":"sh","ix":1,"ks":{"a":0,"k":{"i":[[0.189,0.051],[2.154,-1.153],[0.812,-1.022],[0.333,-1.261],[0,0],[-0.61,-1.781],[-1.502,-1.144],[-1.887,-0.121],[-1.638,0.944],[0,0],[-0.778,1.039],[-0.302,1.259],[0.22,1.274],[0.709,1.084],[70.167,23.415]],"o":[[-2.362,-0.621],[-1.152,0.614],[-0.811,1.023],[0,0],[-0.485,1.82],[0.611,1.782],[1.501,1.141],[1.884,0.117],[0,0],[1.122,-0.651],[0.773,-1.039],[0.3,-1.258],[-0.224,-1.275],[-40.436,-61.713],[-0.186,-0.062]],"v":[[-45.14,-141.365],[-52.169,-140.538],[-55.145,-138.058],[-56.877,-134.597],[-127.427,129.723],[-127.234,135.246],[-123.992,139.731],[-118.795,141.665],[-113.392,140.395],[122.979,3.696],[125.857,1.136],[127.486,-2.346],[127.608,-6.184],[126.197,-9.759],[-44.571,-141.196]],"c":true},"ix":2},"nm":"Path 1","mn":"ADBE Vector Shape - Group","hd":false},{"ty":"fl","c":{"a":0,"k":[0.974557674632,0.831324797986,0.178477478027,1],"ix":4},"o":{"a":0,"k":100,"ix":5},"r":1,"bm":0,"nm":"Fill 1","mn":"ADBE Vector Graphic - Fill","hd":false},{"ty":"tr","p":{"a":0,"k":[127.747,141.683],"ix":2},"a":{"a":0,"k":[0,0],"ix":1},"s":{"a":0,"k":[100,100],"ix":3},"r":{"a":0,"k":0,"ix":6},"o":{"a":0,"k":100,"ix":7},"sk":{"a":0,"k":0,"ix":4},"sa":{"a":0,"k":0,"ix":5},"nm":"Transform"}],"nm":"Group 1","np":4,"cix":2,"bm":0,"ix":2,"mn":"ADBE Vector Group","hd":false}],"ip":19.0000007738859,"op":120.0000048877,"st":-89.0000036250443,"bm":0},{"ddd":0,"ind":9,"ty":4,"nm":"Big Pie Chart","sr":1,"ks":{"o":{"a":0,"k":99.731,"ix":11,"x":"var $bm_rt;\nvar result;\nresult = getAnimationComposerPresetValue();\nfunction getAnimationComposerPresetValue() {\n    var bL = thisLayer;\n    var tTrI = null;\n    var tTrO = null;\n    if (bL.marker.numKeys > 0) {\n        var acmp = 'zzzzzzzzzzzzzzz_AC';\n        for (var i = 1; i <= bL.marker.numKeys; i++) {\n            var m = bL.marker.key(i);\n            var p = m.parameters;\n            if (p.hasOwnProperty(acmp + 'MarkerEnabled') && p.hasOwnProperty(acmp + 'MarkerType') && p.hasOwnProperty(acmp + 'MarkerAppPresetType')) {\n                if (p[acmp + 'MarkerEnabled'] != '1') {\n                    continue;\n                }\n                switch (p[acmp + 'MarkerAppPresetType']) {\n                case '1': {\n                        tTrI = m.time;\n                        break;\n                    }\n                case '2': {\n                        tTrO = m.time;\n                        break;\n                    }\n                }\n            }\n        }\n    }\n    ;\n    function acValMul(val) {\n        acAccM *= val;\n    }\n    function easeInCubic(t) {\n        return $bm_mul($bm_mul(t, t), t);\n    }\n    function upACo(tIn, dIn, tOut, dOut, eFi, eFo) {\n        if (dIn < 0) {\n            dIn = 0;\n        }\n        if (dOut < 0) {\n            dOut = 0;\n        }\n        ac.fade = 1;\n        if (t < tOut) {\n            if (t < $bm_sum(tIn, dIn)) {\n                if (dIn == 0) {\n                    ac.fade = 0;\n                } else {\n                    ac.fade = $bm_div($bm_sub(t, tIn), dIn);\n                    if (ac.fade < 0) {\n                        ac.fade = 0;\n                    }\n                    if (ac.fade > 1) {\n                        ac.fade = 1;\n                    }\n                    if (eFi) {\n                        ac.fade = eFi(ac.fade);\n                    }\n                }\n            }\n        } else {\n            if (dOut == 0) {\n                ac.fade = 0;\n            } else {\n                ac.fade = $bm_div($bm_sub(t, tOut), dOut);\n                if (ac.fade < 0) {\n                    ac.fade = 0;\n                }\n                if (ac.fade > 1) {\n                    ac.fade = 1;\n                }\n                if (eFo) {\n                    ac.fade = eFo(ac.fade);\n                }\n                ac.fade = $bm_sub(1, ac.fade);\n            }\n        }\n        ac.intensity = 1;\n        ac.en = true;\n        ac.t = $bm_sub(t, tIn);\n    }\n    var ac = {};\n    ac.en = false;\n    var v = thisProperty.value;\n    var t = time;\n    var acAccM = 1;\n    ac.en = false;\n    if (tTrI !== null && t < tTrI) {\n        upACo(bL.inPoint, $bm_sub(tTrI, bL.inPoint), bL.outPoint, 0);\n        ac.fade = $bm_sub(1, ac.fade);\n    }\n    if (ac.en) {\n        acValMul($bm_sub(1, easeInCubic(ac.fade)));\n    }\n    ac.en = false;\n    if (tTrO !== null && t >= tTrO) {\n        upACo(0, 0, tTrO, $bm_sub($bm_sub(bL.outPoint, tTrO), thisComp.frameDuration));\n        ac.fade = $bm_sub(1, ac.fade);\n    }\n    if (ac.en) {\n        acValMul($bm_sub(1, easeInCubic(ac.fade)));\n    }\n    v = thisProperty.value;\n    v *= acAccM;\n    return v;\n}\n$bm_rt = result;"},"r":{"a":0,"k":0,"ix":10},"p":{"a":0,"k":[1396,832,0],"ix":2},"a":{"a":0,"k":[127,151,0],"ix":1},"s":{"a":0,"k":[160.927,160.927,100],"ix":6}},"ao":0,"shapes":[{"ty":"gr","it":[{"ind":0,"ty":"sh","ix":1,"ks":{"a":0,"k":{"i":[[0.072,0.02],[1.395,-0.804],[0,0],[0.485,-0.633],[0.201,-0.769],[0,0],[-0.121,-0.815],[-0.44,-0.698],[-0.682,-0.473],[-0.815,-0.159],[-36.251,13.553],[-23.686,30.537],[-4.034,38.374],[16.828,34.717],[0.632,0.542],[0.8,0.244]],"o":[[-1.555,-0.409],[0,0],[-0.689,0.398],[-0.486,0.629],[0,0],[-0.216,0.796],[0.121,0.82],[0.44,0.705],[0.686,0.47],[37.954,7.488],[36.251,-13.558],[23.692,-30.538],[4.031,-38.378],[-0.368,-0.748],[-0.634,-0.541],[-0.072,-0.022]],"v":[[102.205,-150.461],[97.599,-149.844],[-74.168,-50.376],[-75.945,-48.818],[-76.984,-46.699],[-126.614,139.231],[-126.758,141.676],[-125.905,143.974],[-124.199,145.759],[-121.921,146.718],[-8.406,137.438],[83.283,69.982],[125.691,-35.439],[106.11,-147.253],[104.594,-149.209],[102.421,-150.399]],"c":true},"ix":2},"nm":"Path 1","mn":"ADBE Vector Shape - Group","hd":false},{"ty":"fl","c":{"a":0,"k":[0.848966172162,0.911711748909,0.951250741996,1],"ix":4},"o":{"a":0,"k":100,"ix":5},"r":1,"bm":0,"nm":"Fill 1","mn":"ADBE Vector Graphic - Fill","hd":false},{"ty":"tr","p":{"a":0,"k":[126.823,150.663],"ix":2},"a":{"a":0,"k":[0,0],"ix":1},"s":{"a":0,"k":[100,100],"ix":3},"r":{"a":0,"k":0,"ix":6},"o":{"a":0,"k":100,"ix":7},"sk":{"a":0,"k":0,"ix":4},"sa":{"a":0,"k":0,"ix":5},"nm":"Transform"}],"nm":"Group 1","np":4,"cix":2,"bm":0,"ix":1,"mn":"ADBE Vector Group","hd":false}],"ip":19.0000007738859,"op":119.000004846969,"st":-67.0000027289659,"bm":0},{"ddd":0,"ind":10,"ty":4,"nm":"Big Pie chart blue","sr":1,"ks":{"o":{"a":1,"k":[{"i":{"x":[0.833],"y":[0.838]},"o":{"x":[0.167],"y":[0.167]},"t":19,"s":[0]},{"i":{"x":[0.833],"y":[0.838]},"o":{"x":[0.167],"y":[0.171]},"t":20,"s":[7.891]},{"i":{"x":[0.833],"y":[0.838]},"o":{"x":[0.167],"y":[0.172]},"t":21,"s":[15.355]},{"i":{"x":[0.833],"y":[0.838]},"o":{"x":[0.167],"y":[0.172]},"t":22,"s":[22.405]},{"i":{"x":[0.833],"y":[0.838]},"o":{"x":[0.167],"y":[0.172]},"t":23,"s":[29.053]},{"i":{"x":[0.833],"y":[0.839]},"o":{"x":[0.167],"y":[0.172]},"t":24,"s":[35.309]},{"i":{"x":[0.833],"y":[0.839]},"o":{"x":[0.167],"y":[0.172]},"t":25,"s":[41.186]},{"i":{"x":[0.833],"y":[0.839]},"o":{"x":[0.167],"y":[0.172]},"t":26,"s":[46.696]},{"i":{"x":[0.833],"y":[0.839]},"o":{"x":[0.167],"y":[0.173]},"t":27,"s":[51.851]},{"i":{"x":[0.833],"y":[0.839]},"o":{"x":[0.167],"y":[0.173]},"t":28,"s":[56.662]},{"i":{"x":[0.833],"y":[0.84]},"o":{"x":[0.167],"y":[0.173]},"t":29,"s":[61.141]},{"i":{"x":[0.833],"y":[0.84]},"o":{"x":[0.167],"y":[0.173]},"t":30,"s":[65.301]},{"i":{"x":[0.833],"y":[0.84]},"o":{"x":[0.167],"y":[0.174]},"t":31,"s":[69.153]},{"i":{"x":[0.833],"y":[0.84]},"o":{"x":[0.167],"y":[0.174]},"t":32,"s":[72.708]},{"i":{"x":[0.833],"y":[0.841]},"o":{"x":[0.167],"y":[0.174]},"t":33,"s":[75.98]},{"i":{"x":[0.833],"y":[0.841]},"o":{"x":[0.167],"y":[0.175]},"t":34,"s":[78.979]},{"i":{"x":[0.833],"y":[0.841]},"o":{"x":[0.167],"y":[0.175]},"t":35,"s":[81.717]},{"i":{"x":[0.833],"y":[0.842]},"o":{"x":[0.167],"y":[0.175]},"t":36,"s":[84.206]},{"i":{"x":[0.833],"y":[0.842]},"o":{"x":[0.167],"y":[0.176]},"t":37,"s":[86.459]},{"i":{"x":[0.833],"y":[0.843]},"o":{"x":[0.167],"y":[0.176]},"t":38,"s":[88.486]},{"i":{"x":[0.833],"y":[0.843]},"o":{"x":[0.167],"y":[0.177]},"t":39,"s":[90.301]},{"i":{"x":[0.833],"y":[0.844]},"o":{"x":[0.167],"y":[0.178]},"t":40,"s":[91.914]},{"i":{"x":[0.833],"y":[0.844]},"o":{"x":[0.167],"y":[0.179]},"t":41,"s":[93.337]},{"i":{"x":[0.833],"y":[0.845]},"o":{"x":[0.167],"y":[0.179]},"t":42,"s":[94.583]},{"i":{"x":[0.833],"y":[0.846]},"o":{"x":[0.167],"y":[0.181]},"t":43,"s":[95.663]},{"i":{"x":[0.833],"y":[0.847]},"o":{"x":[0.167],"y":[0.182]},"t":44,"s":[96.589]},{"i":{"x":[0.833],"y":[0.848]},"o":{"x":[0.167],"y":[0.183]},"t":45,"s":[97.372]},{"i":{"x":[0.833],"y":[0.85]},"o":{"x":[0.167],"y":[0.185]},"t":46,"s":[98.026]},{"i":{"x":[0.833],"y":[0.852]},"o":{"x":[0.167],"y":[0.187]},"t":47,"s":[98.561]},{"i":{"x":[0.833],"y":[0.854]},"o":{"x":[0.167],"y":[0.19]},"t":48,"s":[98.989]},{"i":{"x":[0.833],"y":[0.857]},"o":{"x":[0.167],"y":[0.194]},"t":49,"s":[99.323]},{"i":{"x":[0.833],"y":[0.861]},"o":{"x":[0.167],"y":[0.2]},"t":50,"s":[99.574]},{"i":{"x":[0.833],"y":[0.866]},"o":{"x":[0.167],"y":[0.208]},"t":51,"s":[99.753]},{"i":{"x":[0.833],"y":[0.874]},"o":{"x":[0.167],"y":[0.221]},"t":52,"s":[99.874]},{"i":{"x":[0.833],"y":[0.886]},"o":{"x":[0.167],"y":[0.246]},"t":53,"s":[99.947]},{"i":{"x":[0.833],"y":[0.905]},"o":{"x":[0.167],"y":[0.31]},"t":54,"s":[99.984]},{"i":{"x":[0.833],"y":[0.917]},"o":{"x":[0.167],"y":[0.667]},"t":55,"s":[99.998]},{"i":{"x":[0.833],"y":[1]},"o":{"x":[0.167],"y":[0]},"t":56,"s":[100]},{"i":{"x":[0.833],"y":[1]},"o":{"x":[0.167],"y":[0]},"t":57,"s":[100]},{"i":{"x":[0.833],"y":[1]},"o":{"x":[0.167],"y":[0]},"t":58,"s":[100]},{"i":{"x":[0.833],"y":[1]},"o":{"x":[0.167],"y":[0]},"t":59,"s":[100]},{"i":{"x":[0.833],"y":[1]},"o":{"x":[0.167],"y":[0]},"t":60,"s":[100]},{"i":{"x":[0.833],"y":[1]},"o":{"x":[0.167],"y":[0]},"t":61,"s":[100]},{"i":{"x":[0.833],"y":[1]},"o":{"x":[0.167],"y":[0]},"t":62,"s":[100]},{"i":{"x":[0.833],"y":[1]},"o":{"x":[0.167],"y":[0]},"t":63,"s":[100]},{"i":{"x":[0.833],"y":[1]},"o":{"x":[0.167],"y":[0]},"t":64,"s":[100]},{"i":{"x":[0.833],"y":[1]},"o":{"x":[0.167],"y":[0]},"t":65,"s":[100]},{"i":{"x":[0.833],"y":[1]},"o":{"x":[0.167],"y":[0]},"t":66,"s":[100]},{"i":{"x":[0.833],"y":[1]},"o":{"x":[0.167],"y":[0]},"t":67,"s":[100]},{"i":{"x":[0.833],"y":[1]},"o":{"x":[0.167],"y":[0]},"t":68,"s":[100]},{"i":{"x":[0.833],"y":[1]},"o":{"x":[0.167],"y":[0]},"t":69,"s":[100]},{"i":{"x":[0.833],"y":[1]},"o":{"x":[0.167],"y":[0]},"t":70,"s":[100]},{"i":{"x":[0.833],"y":[1]},"o":{"x":[0.167],"y":[0]},"t":71,"s":[100]},{"i":{"x":[0.833],"y":[1]},"o":{"x":[0.167],"y":[0]},"t":72,"s":[100]},{"i":{"x":[0.833],"y":[1]},"o":{"x":[0.167],"y":[0]},"t":73,"s":[100]},{"i":{"x":[0.833],"y":[1]},"o":{"x":[0.167],"y":[0]},"t":74,"s":[100]},{"i":{"x":[0.833],"y":[1]},"o":{"x":[0.167],"y":[0]},"t":75,"s":[100]},{"i":{"x":[0.833],"y":[1]},"o":{"x":[0.167],"y":[0]},"t":76,"s":[100]},{"i":{"x":[0.833],"y":[1]},"o":{"x":[0.167],"y":[0]},"t":77,"s":[100]},{"i":{"x":[0.833],"y":[1]},"o":{"x":[0.167],"y":[0]},"t":78,"s":[100]},{"i":{"x":[0.833],"y":[1]},"o":{"x":[0.167],"y":[0]},"t":79,"s":[100]},{"i":{"x":[0.833],"y":[1]},"o":{"x":[0.167],"y":[0]},"t":80,"s":[100]},{"i":{"x":[0.833],"y":[1]},"o":{"x":[0.167],"y":[0]},"t":81,"s":[100]},{"i":{"x":[0.833],"y":[1]},"o":{"x":[0.167],"y":[0]},"t":82,"s":[100]},{"i":{"x":[0.833],"y":[1]},"o":{"x":[0.167],"y":[0]},"t":83,"s":[100]},{"i":{"x":[0.833],"y":[1]},"o":{"x":[0.167],"y":[0]},"t":84,"s":[100]},{"i":{"x":[0.833],"y":[1]},"o":{"x":[0.167],"y":[0]},"t":85,"s":[100]},{"i":{"x":[0.833],"y":[1]},"o":{"x":[0.167],"y":[0]},"t":86,"s":[100]},{"i":{"x":[0.833],"y":[1]},"o":{"x":[0.167],"y":[0]},"t":87,"s":[100]},{"i":{"x":[0.833],"y":[1]},"o":{"x":[0.167],"y":[0]},"t":88,"s":[100]},{"i":{"x":[0.833],"y":[1]},"o":{"x":[0.167],"y":[0]},"t":89,"s":[100]},{"i":{"x":[0.833],"y":[1]},"o":{"x":[0.167],"y":[0]},"t":90,"s":[100]},{"i":{"x":[0.833],"y":[1]},"o":{"x":[0.167],"y":[0]},"t":91,"s":[100]},{"i":{"x":[0.833],"y":[1]},"o":{"x":[0.167],"y":[0]},"t":92,"s":[100]},{"i":{"x":[0.833],"y":[1]},"o":{"x":[0.167],"y":[0]},"t":93,"s":[100]},{"i":{"x":[0.833],"y":[1]},"o":{"x":[0.167],"y":[0]},"t":94,"s":[100]},{"i":{"x":[0.833],"y":[1]},"o":{"x":[0.167],"y":[0]},"t":95,"s":[100]},{"i":{"x":[0.833],"y":[1]},"o":{"x":[0.167],"y":[0]},"t":96,"s":[100]},{"i":{"x":[0.833],"y":[1]},"o":{"x":[0.167],"y":[0]},"t":97,"s":[100]},{"i":{"x":[0.833],"y":[1]},"o":{"x":[0.167],"y":[0]},"t":98,"s":[100]},{"i":{"x":[0.833],"y":[1]},"o":{"x":[0.167],"y":[0]},"t":99,"s":[100]},{"i":{"x":[0.833],"y":[1]},"o":{"x":[0.167],"y":[0]},"t":100,"s":[100]},{"i":{"x":[0.833],"y":[1]},"o":{"x":[0.167],"y":[0]},"t":101,"s":[100]},{"i":{"x":[0.833],"y":[1]},"o":{"x":[0.167],"y":[0]},"t":102,"s":[100]},{"i":{"x":[0.833],"y":[1]},"o":{"x":[0.167],"y":[0]},"t":103,"s":[100]},{"i":{"x":[0.833],"y":[1.003]},"o":{"x":[0.167],"y":[0]},"t":104,"s":[100]},{"i":{"x":[0.833],"y":[0.333]},"o":{"x":[0.167],"y":[0.083]},"t":105,"s":[100]},{"i":{"x":[0.833],"y":[0.69]},"o":{"x":[0.167],"y":[0.095]},"t":106,"s":[99.964]},{"i":{"x":[0.833],"y":[0.754]},"o":{"x":[0.167],"y":[0.114]},"t":107,"s":[99.708]},{"i":{"x":[0.833],"y":[0.779]},"o":{"x":[0.167],"y":[0.126]},"t":108,"s":[99.016]},{"i":{"x":[0.833],"y":[0.792]},"o":{"x":[0.167],"y":[0.134]},"t":109,"s":[97.668]},{"i":{"x":[0.833],"y":[0.8]},"o":{"x":[0.167],"y":[0.139]},"t":110,"s":[95.445]},{"i":{"x":[0.833],"y":[0.806]},"o":{"x":[0.167],"y":[0.143]},"t":111,"s":[92.128]},{"i":{"x":[0.833],"y":[0.81]},"o":{"x":[0.167],"y":[0.146]},"t":112,"s":[87.5]},{"i":{"x":[0.833],"y":[0.813]},"o":{"x":[0.167],"y":[0.148]},"t":113,"s":[81.341]},{"i":{"x":[0.833],"y":[0.815]},"o":{"x":[0.167],"y":[0.15]},"t":114,"s":[73.433]},{"i":{"x":[0.833],"y":[0.817]},"o":{"x":[0.167],"y":[0.152]},"t":115,"s":[63.557]},{"i":{"x":[0.833],"y":[0.818]},"o":{"x":[0.167],"y":[0.153]},"t":116,"s":[51.494]},{"i":{"x":[0.833],"y":[0.819]},"o":{"x":[0.167],"y":[0.154]},"t":117,"s":[37.026]},{"i":{"x":[0.833],"y":[0.833]},"o":{"x":[0.167],"y":[0.155]},"t":118,"s":[19.934]},{"t":119.000004846969,"s":[0]}],"ix":11},"r":{"a":0,"k":0,"ix":10},"p":{"a":0,"k":[1116,732,0],"ix":2},"a":{"a":0,"k":[126,201,0],"ix":1},"s":{"a":0,"k":[161.696,161.696,100],"ix":6}},"ao":0,"shapes":[{"ty":"gr","it":[{"ind":0,"ty":"sh","ix":1,"ks":{"a":0,"k":{"i":[[1.213,0.318],[0.099,0.03],[24.961,46.101],[-13.508,50.615],[-44.663,27.717],[-51.629,-10.197],[-0.534,-0.368],[-0.345,-0.551],[-0.094,-0.634],[0.17,-0.62],[0,0],[1.088,-0.626]],"o":[[-0.099,-0.026],[-49.914,-16.621],[-24.964,-46.104],[13.511,-50.619],[44.664,-27.716],[0.636,0.124],[0.538,0.368],[0.341,0.543],[0.099,0.635],[0,0],[-0.326,1.205],[-1.084,0.625]],"v":[[16.007,200.633],[15.711,200.546],[-100.841,102.916],[-118.67,-47.638],[-28.115,-169.575],[121.777,-196.847],[123.554,-196.102],[124.889,-194.709],[125.552,-192.923],[125.443,-191.021],[21.803,197.297],[19.597,200.155]],"c":true},"ix":2},"nm":"Path 1","mn":"ADBE Vector Shape - Group","hd":false},{"ty":"fl","c":{"a":0,"k":[0.245965770647,0.704548076555,0.884769215303,1],"ix":4},"o":{"a":0,"k":100,"ix":5},"r":1,"bm":0,"nm":"Fill 1","mn":"ADBE Vector Graphic - Fill","hd":false},{"ty":"tr","p":{"a":0,"k":[125.605,200.79],"ix":2},"a":{"a":0,"k":[0,0],"ix":1},"s":{"a":0,"k":[100,100],"ix":3},"r":{"a":0,"k":0,"ix":6},"o":{"a":0,"k":100,"ix":7},"sk":{"a":0,"k":0,"ix":4},"sa":{"a":0,"k":0,"ix":5},"nm":"Transform"}],"nm":"Group 1","np":4,"cix":2,"bm":0,"ix":1,"mn":"ADBE Vector Group","hd":false}],"ip":19.0000007738859,"op":120.0000048877,"st":-82.0000033399285,"bm":0},{"ddd":0,"ind":11,"ty":4,"nm":"REctangle 3","td":1,"sr":1,"ks":{"o":{"a":0,"k":100,"ix":11},"r":{"a":0,"k":0,"ix":10},"p":{"a":1,"k":[{"i":{"x":0.667,"y":1},"o":{"x":0.222,"y":0},"t":28,"s":[1688,125,0],"to":[91.524,0,0],"ti":[-58.476,0,0]},{"t":52.0000021180034,"s":[2588,149,0]}],"ix":2},"a":{"a":0,"k":[0,0,0],"ix":1},"s":{"a":0,"k":[111.468,209.468,100],"ix":6}},"ao":0,"shapes":[{"ty":"gr","it":[{"ty":"rc","d":1,"s":{"a":0,"k":[260.797,283.016],"ix":2},"p":{"a":0,"k":[0,0],"ix":3},"r":{"a":0,"k":0,"ix":4},"nm":"Rectangle Path 1","mn":"ADBE Vector Shape - Rect","hd":false},{"ty":"st","c":{"a":0,"k":[1,1,1,1],"ix":3},"o":{"a":0,"k":100,"ix":4},"w":{"a":0,"k":2,"ix":5},"lc":1,"lj":1,"ml":4,"bm":0,"nm":"Stroke 1","mn":"ADBE Vector Graphic - Stroke","hd":false},{"ty":"fl","c":{"a":0,"k":[0,0.305881993911,0.439215985466,1],"ix":4},"o":{"a":0,"k":100,"ix":5},"r":1,"bm":0,"nm":"Fill 1","mn":"ADBE Vector Graphic - Fill","hd":false},{"ty":"tr","p":{"a":0,"k":[-721.602,400.508],"ix":2},"a":{"a":0,"k":[0,0],"ix":1},"s":{"a":0,"k":[249.061,117.215],"ix":3},"r":{"a":0,"k":0,"ix":6},"o":{"a":0,"k":100,"ix":7},"sk":{"a":0,"k":0,"ix":4},"sa":{"a":0,"k":0,"ix":5},"nm":"Transform"}],"nm":"Rectangle 1","np":3,"cix":2,"bm":0,"ix":1,"mn":"ADBE Vector Group","hd":false}],"ip":-12.00000048877,"op":106.000004317469,"st":-12.00000048877,"bm":0},{"ddd":0,"ind":12,"ty":4,"nm":"Artwork 8 Outlines 2","tt":1,"sr":1,"ks":{"o":{"a":1,"k":[{"i":{"x":[0.833],"y":[0.835]},"o":{"x":[0.167],"y":[0.167]},"t":9,"s":[0]},{"i":{"x":[0.833],"y":[0.835]},"o":{"x":[0.167],"y":[0.168]},"t":10,"s":[3.093]},{"i":{"x":[0.833],"y":[0.835]},"o":{"x":[0.167],"y":[0.168]},"t":11,"s":[6.121]},{"i":{"x":[0.833],"y":[0.835]},"o":{"x":[0.167],"y":[0.168]},"t":12,"s":[9.085]},{"i":{"x":[0.833],"y":[0.835]},"o":{"x":[0.167],"y":[0.168]},"t":13,"s":[11.986]},{"i":{"x":[0.833],"y":[0.835]},"o":{"x":[0.167],"y":[0.169]},"t":14,"s":[14.825]},{"i":{"x":[0.833],"y":[0.835]},"o":{"x":[0.167],"y":[0.169]},"t":15,"s":[17.603]},{"i":{"x":[0.833],"y":[0.835]},"o":{"x":[0.167],"y":[0.169]},"t":16,"s":[20.319]},{"i":{"x":[0.833],"y":[0.835]},"o":{"x":[0.167],"y":[0.169]},"t":17,"s":[22.975]},{"i":{"x":[0.833],"y":[0.835]},"o":{"x":[0.167],"y":[0.169]},"t":18,"s":[25.571]},{"i":{"x":[0.833],"y":[0.835]},"o":{"x":[0.167],"y":[0.169]},"t":19,"s":[28.108]},{"i":{"x":[0.833],"y":[0.835]},"o":{"x":[0.167],"y":[0.169]},"t":20,"s":[30.587]},{"i":{"x":[0.833],"y":[0.835]},"o":{"x":[0.167],"y":[0.169]},"t":21,"s":[33.008]},{"i":{"x":[0.833],"y":[0.835]},"o":{"x":[0.167],"y":[0.169]},"t":22,"s":[35.372]},{"i":{"x":[0.833],"y":[0.835]},"o":{"x":[0.167],"y":[0.169]},"t":23,"s":[37.68]},{"i":{"x":[0.833],"y":[0.835]},"o":{"x":[0.167],"y":[0.169]},"t":24,"s":[39.932]},{"i":{"x":[0.833],"y":[0.835]},"o":{"x":[0.167],"y":[0.169]},"t":25,"s":[42.13]},{"i":{"x":[0.833],"y":[0.835]},"o":{"x":[0.167],"y":[0.169]},"t":26,"s":[44.273]},{"i":{"x":[0.833],"y":[0.835]},"o":{"x":[0.167],"y":[0.169]},"t":27,"s":[46.362]},{"i":{"x":[0.833],"y":[0.835]},"o":{"x":[0.167],"y":[0.169]},"t":28,"s":[48.399]},{"i":{"x":[0.833],"y":[0.836]},"o":{"x":[0.167],"y":[0.169]},"t":29,"s":[50.383]},{"i":{"x":[0.833],"y":[0.836]},"o":{"x":[0.167],"y":[0.169]},"t":30,"s":[52.316]},{"i":{"x":[0.833],"y":[0.836]},"o":{"x":[0.167],"y":[0.169]},"t":31,"s":[54.198]},{"i":{"x":[0.833],"y":[0.836]},"o":{"x":[0.167],"y":[0.169]},"t":32,"s":[56.03]},{"i":{"x":[0.833],"y":[0.836]},"o":{"x":[0.167],"y":[0.169]},"t":33,"s":[57.812]},{"i":{"x":[0.833],"y":[0.836]},"o":{"x":[0.167],"y":[0.169]},"t":34,"s":[59.546]},{"i":{"x":[0.833],"y":[0.836]},"o":{"x":[0.167],"y":[0.169]},"t":35,"s":[61.231]},{"i":{"x":[0.833],"y":[0.836]},"o":{"x":[0.167],"y":[0.169]},"t":36,"s":[62.869]},{"i":{"x":[0.833],"y":[0.836]},"o":{"x":[0.167],"y":[0.169]},"t":37,"s":[64.46]},{"i":{"x":[0.833],"y":[0.836]},"o":{"x":[0.167],"y":[0.169]},"t":38,"s":[66.005]},{"i":{"x":[0.833],"y":[0.836]},"o":{"x":[0.167],"y":[0.169]},"t":39,"s":[67.505]},{"i":{"x":[0.833],"y":[0.836]},"o":{"x":[0.167],"y":[0.169]},"t":40,"s":[68.96]},{"i":{"x":[0.833],"y":[0.836]},"o":{"x":[0.167],"y":[0.169]},"t":41,"s":[70.37]},{"i":{"x":[0.833],"y":[0.836]},"o":{"x":[0.167],"y":[0.169]},"t":42,"s":[71.738]},{"i":{"x":[0.833],"y":[0.836]},"o":{"x":[0.167],"y":[0.169]},"t":43,"s":[73.062]},{"i":{"x":[0.833],"y":[0.836]},"o":{"x":[0.167],"y":[0.169]},"t":44,"s":[74.345]},{"i":{"x":[0.833],"y":[0.836]},"o":{"x":[0.167],"y":[0.169]},"t":45,"s":[75.586]},{"i":{"x":[0.833],"y":[0.836]},"o":{"x":[0.167],"y":[0.17]},"t":46,"s":[76.786]},{"i":{"x":[0.833],"y":[0.836]},"o":{"x":[0.167],"y":[0.17]},"t":47,"s":[77.947]},{"i":{"x":[0.833],"y":[0.836]},"o":{"x":[0.167],"y":[0.17]},"t":48,"s":[79.068]},{"i":{"x":[0.833],"y":[0.836]},"o":{"x":[0.167],"y":[0.17]},"t":49,"s":[80.15]},{"i":{"x":[0.833],"y":[0.836]},"o":{"x":[0.167],"y":[0.17]},"t":50,"s":[81.195]},{"i":{"x":[0.833],"y":[0.836]},"o":{"x":[0.167],"y":[0.17]},"t":51,"s":[82.202]},{"i":{"x":[0.833],"y":[0.836]},"o":{"x":[0.167],"y":[0.17]},"t":52,"s":[83.173]},{"i":{"x":[0.833],"y":[0.837]},"o":{"x":[0.167],"y":[0.17]},"t":53,"s":[84.107]},{"i":{"x":[0.833],"y":[0.837]},"o":{"x":[0.167],"y":[0.17]},"t":54,"s":[85.007]},{"i":{"x":[0.833],"y":[0.837]},"o":{"x":[0.167],"y":[0.17]},"t":55,"s":[85.871]},{"i":{"x":[0.833],"y":[0.837]},"o":{"x":[0.167],"y":[0.17]},"t":56,"s":[86.702]},{"i":{"x":[0.833],"y":[0.837]},"o":{"x":[0.167],"y":[0.17]},"t":57,"s":[87.5]},{"i":{"x":[0.833],"y":[0.837]},"o":{"x":[0.167],"y":[0.17]},"t":58,"s":[88.265]},{"i":{"x":[0.833],"y":[0.837]},"o":{"x":[0.167],"y":[0.17]},"t":59,"s":[88.998]},{"i":{"x":[0.833],"y":[0.837]},"o":{"x":[0.167],"y":[0.17]},"t":60,"s":[89.7]},{"i":{"x":[0.833],"y":[0.837]},"o":{"x":[0.167],"y":[0.171]},"t":61,"s":[90.372]},{"i":{"x":[0.833],"y":[0.837]},"o":{"x":[0.167],"y":[0.171]},"t":62,"s":[91.013]},{"i":{"x":[0.833],"y":[0.837]},"o":{"x":[0.167],"y":[0.171]},"t":63,"s":[91.626]},{"i":{"x":[0.833],"y":[0.837]},"o":{"x":[0.167],"y":[0.171]},"t":64,"s":[92.21]},{"i":{"x":[0.833],"y":[0.837]},"o":{"x":[0.167],"y":[0.171]},"t":65,"s":[92.766]},{"i":{"x":[0.833],"y":[0.838]},"o":{"x":[0.167],"y":[0.171]},"t":66,"s":[93.295]},{"i":{"x":[0.833],"y":[0.838]},"o":{"x":[0.167],"y":[0.171]},"t":67,"s":[93.798]},{"i":{"x":[0.833],"y":[0.838]},"o":{"x":[0.167],"y":[0.171]},"t":68,"s":[94.275]},{"i":{"x":[0.833],"y":[0.838]},"o":{"x":[0.167],"y":[0.171]},"t":69,"s":[94.727]},{"i":{"x":[0.833],"y":[0.838]},"o":{"x":[0.167],"y":[0.172]},"t":70,"s":[95.154]},{"i":{"x":[0.833],"y":[0.838]},"o":{"x":[0.167],"y":[0.172]},"t":71,"s":[95.558]},{"i":{"x":[0.833],"y":[0.838]},"o":{"x":[0.167],"y":[0.172]},"t":72,"s":[95.938]},{"i":{"x":[0.833],"y":[0.839]},"o":{"x":[0.167],"y":[0.172]},"t":73,"s":[96.296]},{"i":{"x":[0.833],"y":[0.839]},"o":{"x":[0.167],"y":[0.172]},"t":74,"s":[96.633]},{"i":{"x":[0.833],"y":[0.839]},"o":{"x":[0.167],"y":[0.172]},"t":75,"s":[96.948]},{"i":{"x":[0.833],"y":[0.839]},"o":{"x":[0.167],"y":[0.173]},"t":76,"s":[97.243]},{"i":{"x":[0.833],"y":[0.839]},"o":{"x":[0.167],"y":[0.173]},"t":77,"s":[97.519]},{"i":{"x":[0.833],"y":[0.84]},"o":{"x":[0.167],"y":[0.173]},"t":78,"s":[97.775]},{"i":{"x":[0.833],"y":[0.84]},"o":{"x":[0.167],"y":[0.173]},"t":79,"s":[98.013]},{"i":{"x":[0.833],"y":[0.84]},"o":{"x":[0.167],"y":[0.174]},"t":80,"s":[98.234]},{"i":{"x":[0.833],"y":[0.84]},"o":{"x":[0.167],"y":[0.174]},"t":81,"s":[98.438]},{"i":{"x":[0.833],"y":[0.841]},"o":{"x":[0.167],"y":[0.174]},"t":82,"s":[98.625]},{"i":{"x":[0.833],"y":[0.841]},"o":{"x":[0.167],"y":[0.175]},"t":83,"s":[98.796]},{"i":{"x":[0.833],"y":[0.841]},"o":{"x":[0.167],"y":[0.175]},"t":84,"s":[98.953]},{"i":{"x":[0.833],"y":[0.842]},"o":{"x":[0.167],"y":[0.175]},"t":85,"s":[99.096]},{"i":{"x":[0.833],"y":[0.842]},"o":{"x":[0.167],"y":[0.176]},"t":86,"s":[99.225]},{"i":{"x":[0.833],"y":[0.843]},"o":{"x":[0.167],"y":[0.176]},"t":87,"s":[99.341]},{"i":{"x":[0.833],"y":[0.843]},"o":{"x":[0.167],"y":[0.177]},"t":88,"s":[99.445]},{"i":{"x":[0.833],"y":[0.844]},"o":{"x":[0.167],"y":[0.178]},"t":89,"s":[99.537]},{"i":{"x":[0.833],"y":[0.844]},"o":{"x":[0.167],"y":[0.179]},"t":90,"s":[99.619]},{"i":{"x":[0.833],"y":[0.845]},"o":{"x":[0.167],"y":[0.179]},"t":91,"s":[99.69]},{"i":{"x":[0.833],"y":[0.846]},"o":{"x":[0.167],"y":[0.181]},"t":92,"s":[99.752]},{"i":{"x":[0.833],"y":[0.847]},"o":{"x":[0.167],"y":[0.182]},"t":93,"s":[99.805]},{"i":{"x":[0.833],"y":[0.848]},"o":{"x":[0.167],"y":[0.183]},"t":94,"s":[99.85]},{"i":{"x":[0.833],"y":[0.85]},"o":{"x":[0.167],"y":[0.185]},"t":95,"s":[99.887]},{"i":{"x":[0.833],"y":[0.852]},"o":{"x":[0.167],"y":[0.187]},"t":96,"s":[99.918]},{"i":{"x":[0.833],"y":[0.854]},"o":{"x":[0.167],"y":[0.19]},"t":97,"s":[99.942]},{"i":{"x":[0.833],"y":[0.857]},"o":{"x":[0.167],"y":[0.194]},"t":98,"s":[99.961]},{"i":{"x":[0.833],"y":[0.861]},"o":{"x":[0.167],"y":[0.2]},"t":99,"s":[99.976]},{"i":{"x":[0.833],"y":[0.866]},"o":{"x":[0.167],"y":[0.208]},"t":100,"s":[99.986]},{"i":{"x":[0.833],"y":[0.874]},"o":{"x":[0.167],"y":[0.221]},"t":101,"s":[99.993]},{"i":{"x":[0.833],"y":[0.886]},"o":{"x":[0.167],"y":[0.246]},"t":102,"s":[99.997]},{"i":{"x":[0.833],"y":[0.905]},"o":{"x":[0.167],"y":[0.31]},"t":103,"s":[99.999]},{"i":{"x":[0.833],"y":[0.917]},"o":{"x":[0.167],"y":[0.667]},"t":104,"s":[100]},{"i":{"x":[0.833],"y":[1]},"o":{"x":[0.167],"y":[0]},"t":105,"s":[100]},{"i":{"x":[0.833],"y":[1]},"o":{"x":[0.167],"y":[0]},"t":106,"s":[100]},{"i":{"x":[0.833],"y":[1]},"o":{"x":[0.167],"y":[0]},"t":107,"s":[100]},{"i":{"x":[0.833],"y":[1]},"o":{"x":[0.167],"y":[0]},"t":108,"s":[100]},{"i":{"x":[0.833],"y":[1]},"o":{"x":[0.167],"y":[0]},"t":109,"s":[100]},{"i":{"x":[0.833],"y":[1]},"o":{"x":[0.167],"y":[0]},"t":110,"s":[100]},{"i":{"x":[0.833],"y":[1]},"o":{"x":[0.167],"y":[0]},"t":111,"s":[100]},{"i":{"x":[0.833],"y":[1.006]},"o":{"x":[0.167],"y":[0]},"t":112,"s":[100]},{"i":{"x":[0.833],"y":[0.333]},"o":{"x":[0.167],"y":[0.083]},"t":113,"s":[100]},{"i":{"x":[0.833],"y":[0.69]},"o":{"x":[0.167],"y":[0.095]},"t":114,"s":[99.925]},{"i":{"x":[0.833],"y":[0.754]},"o":{"x":[0.167],"y":[0.114]},"t":115,"s":[99.399]},{"i":{"x":[0.833],"y":[0.779]},"o":{"x":[0.167],"y":[0.126]},"t":116,"s":[97.971]},{"i":{"x":[0.833],"y":[0.792]},"o":{"x":[0.167],"y":[0.134]},"t":117,"s":[95.192]},{"i":{"x":[0.833],"y":[0.8]},"o":{"x":[0.167],"y":[0.139]},"t":118,"s":[90.609]},{"i":{"x":[0.833],"y":[0.806]},"o":{"x":[0.167],"y":[0.143]},"t":119,"s":[83.772]},{"i":{"x":[0.833],"y":[0.81]},"o":{"x":[0.167],"y":[0.146]},"t":120,"s":[74.23]},{"i":{"x":[0.833],"y":[0.813]},"o":{"x":[0.167],"y":[0.148]},"t":121,"s":[61.533]},{"i":{"x":[0.833],"y":[0.815]},"o":{"x":[0.167],"y":[0.15]},"t":122,"s":[45.229]},{"i":{"x":[0.833],"y":[0.833]},"o":{"x":[0.167],"y":[0.152]},"t":123,"s":[24.869]},{"t":124.000005050624,"s":[0]}],"ix":11},"r":{"a":0,"k":0,"ix":10},"p":{"a":0,"k":[1656,928,0],"ix":2},"a":{"a":0,"k":[136,89,0],"ix":1},"s":{"a":0,"k":[171.91,171.91,100],"ix":6}},"ao":0,"shapes":[{"ty":"gr","it":[{"ind":0,"ty":"sh","ix":1,"ks":{"a":0,"k":{"i":[[0,0],[0,0],[0,0],[0,0]],"o":[[0,0],[0,0],[0,0],[0,0]],"v":[[-135.742,88.661],[135.742,88.661],[135.742,-88.661],[-135.742,-88.661]],"c":true},"ix":2},"nm":"Path 1","mn":"ADBE Vector Shape - Group","hd":false},{"ind":1,"ty":"sh","ix":2,"ks":{"a":0,"k":{"i":[[0,0]],"o":[[0,0]],"v":[[-135.742,-88.661]],"c":false},"ix":2},"nm":"Path 2","mn":"ADBE Vector Shape - Group","hd":false},{"ind":2,"ty":"sh","ix":3,"ks":{"a":0,"k":{"i":[[0,0],[0,0],[0,0],[0,0]],"o":[[0,0],[0,0],[0,0],[0,0]],"v":[[-120.58,-73.497],[120.578,-73.497],[120.578,73.496],[-120.58,73.496]],"c":true},"ix":2},"nm":"Path 3","mn":"ADBE Vector Shape - Group","hd":false},{"ty":"mm","mm":1,"nm":"Merge Paths 1","mn":"ADBE Vector Filter - Merge","hd":false},{"ty":"fl","c":{"a":0,"k":[0.139809686997,0.407291098202,0.536257455863,1],"ix":4},"o":{"a":0,"k":100,"ix":5},"r":1,"bm":0,"nm":"Fill 1","mn":"ADBE Vector Graphic - Fill","hd":false},{"ty":"tr","p":{"a":0,"k":[135.742,88.661],"ix":2},"a":{"a":0,"k":[0,0],"ix":1},"s":{"a":0,"k":[100,100],"ix":3},"r":{"a":0,"k":0,"ix":6},"o":{"a":0,"k":100,"ix":7},"sk":{"a":0,"k":0,"ix":4},"sa":{"a":0,"k":0,"ix":5},"nm":"Transform"}],"nm":"Group 1","np":5,"cix":2,"bm":0,"ix":1,"mn":"ADBE Vector Group","hd":false}],"ip":9.00000036657752,"op":125.000005091354,"st":-12.00000048877,"bm":0}]},{"id":"comp_1","layers":[{"ddd":0,"ind":1,"ty":4,"nm":"Artwork 5 Outlines","sr":1,"ks":{"o":{"a":0,"k":100,"ix":11,"x":"var $bm_rt;\nvar result;\nresult = getAnimationComposerPresetValue();\nfunction getAnimationComposerPresetValue() {\n    var bL = thisLayer;\n    var tTrI = null;\n    var tTrO = null;\n    if (bL.marker.numKeys > 0) {\n        var acmp = 'zzzzzzzzzzzzzzz_AC';\n        for (var i = 1; i <= bL.marker.numKeys; i++) {\n            var m = bL.marker.key(i);\n            var p = m.parameters;\n            if (p.hasOwnProperty(acmp + 'MarkerEnabled') && p.hasOwnProperty(acmp + 'MarkerType') && p.hasOwnProperty(acmp + 'MarkerAppPresetType')) {\n                if (p[acmp + 'MarkerEnabled'] != '1') {\n                    continue;\n                }\n                switch (p[acmp + 'MarkerAppPresetType']) {\n                case '1': {\n                        tTrI = m.time;\n                        break;\n                    }\n                case '2': {\n                        tTrO = m.time;\n                        break;\n                    }\n                }\n            }\n        }\n    }\n    ;\n    function acValMul(val) {\n        acAccM *= val;\n    }\n    function easeInCubic(t) {\n        return $bm_mul($bm_mul(t, t), t);\n    }\n    function upACo(tIn, dIn, tOut, dOut, eFi, eFo) {\n        if (dIn < 0) {\n            dIn = 0;\n        }\n        if (dOut < 0) {\n            dOut = 0;\n        }\n        ac.fade = 1;\n        if (t < tOut) {\n            if (t < $bm_sum(tIn, dIn)) {\n                if (dIn == 0) {\n                    ac.fade = 0;\n                } else {\n                    ac.fade = $bm_div($bm_sub(t, tIn), dIn);\n                    if (ac.fade < 0) {\n                        ac.fade = 0;\n                    }\n                    if (ac.fade > 1) {\n                        ac.fade = 1;\n                    }\n                    if (eFi) {\n                        ac.fade = eFi(ac.fade);\n                    }\n                }\n            }\n        } else {\n            if (dOut == 0) {\n                ac.fade = 0;\n            } else {\n                ac.fade = $bm_div($bm_sub(t, tOut), dOut);\n                if (ac.fade < 0) {\n                    ac.fade = 0;\n                }\n                if (ac.fade > 1) {\n                    ac.fade = 1;\n                }\n                if (eFo) {\n                    ac.fade = eFo(ac.fade);\n                }\n                ac.fade = $bm_sub(1, ac.fade);\n            }\n        }\n        ac.intensity = 1;\n        ac.en = true;\n        ac.t = $bm_sub(t, tIn);\n    }\n    var ac = {};\n    ac.en = false;\n    var v = thisProperty.value;\n    var t = time;\n    var acAccM = 1;\n    ac.en = false;\n    if (tTrI !== null && t < tTrI) {\n        upACo(bL.inPoint, $bm_sub(tTrI, bL.inPoint), bL.outPoint, 0);\n        ac.fade = $bm_sub(1, ac.fade);\n    }\n    if (ac.en) {\n        acValMul($bm_sub(1, easeInCubic(ac.fade)));\n    }\n    ac.en = false;\n    if (tTrO !== null && t >= tTrO) {\n        upACo(0, 0, tTrO, $bm_sub($bm_sub(bL.outPoint, tTrO), thisComp.frameDuration));\n        ac.fade = $bm_sub(1, ac.fade);\n    }\n    if (ac.en) {\n        acValMul($bm_sub(1, easeInCubic(ac.fade)));\n    }\n    v = thisProperty.value;\n    v *= acAccM;\n    return v;\n}\n$bm_rt = result;"},"r":{"a":0,"k":0,"ix":10},"p":{"a":0,"k":[720,792,0],"ix":2},"a":{"a":0,"k":[45.5,163,0],"ix":1},"s":{"a":0,"k":[168.496,168.496,100],"ix":6}},"ao":0,"shapes":[{"ty":"gr","it":[{"ind":0,"ty":"sh","ix":1,"ks":{"a":0,"k":{"i":[[2.043,0],[0,0],[1.445,1.436],[0.003,2.032],[0,0],[-1.445,1.438],[-2.043,0.002],[0,0],[-1.445,-1.439],[-0.002,-2.034],[0,0],[1.445,-1.438]],"o":[[0,0],[-2.043,0],[-1.445,-1.438],[0,0],[0.003,-2.034],[1.445,-1.439],[0,0],[2.043,0.002],[1.445,1.438],[0,0],[-0.002,2.032],[-1.445,1.436]],"v":[[37.734,162.835],[-37.734,162.835],[-43.182,160.587],[-45.441,155.165],[-45.441,-155.163],[-43.182,-160.585],[-37.734,-162.835],[37.734,-162.835],[43.182,-160.585],[45.441,-155.163],[45.441,155.165],[43.182,160.587]],"c":true},"ix":2},"nm":"Path 1","mn":"ADBE Vector Shape - Group","hd":false},{"ty":"fl","c":{"a":0,"k":[0.139809686997,0.407291098202,0.536257455863,1],"ix":4},"o":{"a":0,"k":100,"ix":5},"r":1,"bm":0,"nm":"Fill 1","mn":"ADBE Vector Graphic - Fill","hd":false},{"ty":"tr","p":{"a":0,"k":[45.442,162.835],"ix":2},"a":{"a":0,"k":[0,0],"ix":1},"s":{"a":0,"k":[100,100],"ix":3},"r":{"a":0,"k":0,"ix":6},"o":{"a":0,"k":100,"ix":7},"sk":{"a":0,"k":0,"ix":4},"sa":{"a":0,"k":0,"ix":5},"nm":"Transform"}],"nm":"Group 1","np":4,"cix":2,"bm":0,"ix":1,"mn":"ADBE Vector Group","hd":false}],"ip":0,"op":143.000005824509,"st":-61.0000024845809,"bm":0},{"ddd":0,"ind":2,"ty":4,"nm":"Artwork 6 Outlines","sr":1,"ks":{"o":{"a":0,"k":100,"ix":11,"x":"var $bm_rt;\nvar result;\nresult = getAnimationComposerPresetValue();\nfunction getAnimationComposerPresetValue() {\n    var bL = thisLayer;\n    var tTrI = null;\n    var tTrO = null;\n    if (bL.marker.numKeys > 0) {\n        var acmp = 'zzzzzzzzzzzzzzz_AC';\n        for (var i = 1; i <= bL.marker.numKeys; i++) {\n            var m = bL.marker.key(i);\n            var p = m.parameters;\n            if (p.hasOwnProperty(acmp + 'MarkerEnabled') && p.hasOwnProperty(acmp + 'MarkerType') && p.hasOwnProperty(acmp + 'MarkerAppPresetType')) {\n                if (p[acmp + 'MarkerEnabled'] != '1') {\n                    continue;\n                }\n                switch (p[acmp + 'MarkerAppPresetType']) {\n                case '1': {\n                        tTrI = m.time;\n                        break;\n                    }\n                case '2': {\n                        tTrO = m.time;\n                        break;\n                    }\n                }\n            }\n        }\n    }\n    ;\n    function acValMul(val) {\n        acAccM *= val;\n    }\n    function easeInCubic(t) {\n        return $bm_mul($bm_mul(t, t), t);\n    }\n    function upACo(tIn, dIn, tOut, dOut, eFi, eFo) {\n        if (dIn < 0) {\n            dIn = 0;\n        }\n        if (dOut < 0) {\n            dOut = 0;\n        }\n        ac.fade = 1;\n        if (t < tOut) {\n            if (t < $bm_sum(tIn, dIn)) {\n                if (dIn == 0) {\n                    ac.fade = 0;\n                } else {\n                    ac.fade = $bm_div($bm_sub(t, tIn), dIn);\n                    if (ac.fade < 0) {\n                        ac.fade = 0;\n                    }\n                    if (ac.fade > 1) {\n                        ac.fade = 1;\n                    }\n                    if (eFi) {\n                        ac.fade = eFi(ac.fade);\n                    }\n                }\n            }\n        } else {\n            if (dOut == 0) {\n                ac.fade = 0;\n            } else {\n                ac.fade = $bm_div($bm_sub(t, tOut), dOut);\n                if (ac.fade < 0) {\n                    ac.fade = 0;\n                }\n                if (ac.fade > 1) {\n                    ac.fade = 1;\n                }\n                if (eFo) {\n                    ac.fade = eFo(ac.fade);\n                }\n                ac.fade = $bm_sub(1, ac.fade);\n            }\n        }\n        ac.intensity = 1;\n        ac.en = true;\n        ac.t = $bm_sub(t, tIn);\n    }\n    var ac = {};\n    ac.en = false;\n    var v = thisProperty.value;\n    var t = time;\n    var acAccM = 1;\n    ac.en = false;\n    if (tTrI !== null && t < tTrI) {\n        upACo(bL.inPoint, $bm_sub(tTrI, bL.inPoint), bL.outPoint, 0);\n        ac.fade = $bm_sub(1, ac.fade);\n    }\n    if (ac.en) {\n        acValMul($bm_sub(1, easeInCubic(ac.fade)));\n    }\n    ac.en = false;\n    if (tTrO !== null && t >= tTrO) {\n        upACo(0, 0, tTrO, $bm_sub($bm_sub(bL.outPoint, tTrO), thisComp.frameDuration));\n        ac.fade = $bm_sub(1, ac.fade);\n    }\n    if (ac.en) {\n        acValMul($bm_sub(1, easeInCubic(ac.fade)));\n    }\n    v = thisProperty.value;\n    v *= acAccM;\n    return v;\n}\n$bm_rt = result;"},"r":{"a":0,"k":0,"ix":10},"p":{"a":0,"k":[492,856,0],"ix":2},"a":{"a":0,"k":[45.5,128.5,0],"ix":1},"s":{"a":0,"k":[165.37,165.37,100],"ix":6}},"ao":0,"shapes":[{"ty":"gr","it":[{"ind":0,"ty":"sh","ix":1,"ks":{"a":0,"k":{"i":[[1.997,0.042],[0,0],[1.445,1.376],[0.049,1.99],[0,0],[-1.445,1.376],[-1.997,-0.041],[0,0],[-1.445,-1.373],[-0.05,-1.99],[0,0],[1.445,-1.373]],"o":[[0,0],[-1.997,0.042],[-1.445,-1.373],[0,0],[0.049,-1.99],[1.445,-1.373],[0,0],[1.997,-0.041],[1.445,1.376],[0,0],[-0.05,1.99],[-1.445,1.376]],"v":[[37.734,128.066],[-37.734,128.066],[-43.109,125.984],[-45.441,120.734],[-45.441,-120.733],[-43.109,-125.987],[-37.734,-128.066],[37.734,-128.066],[43.107,-125.987],[45.441,-120.733],[45.441,120.734],[43.107,125.984]],"c":true},"ix":2},"nm":"Path 1","mn":"ADBE Vector Shape - Group","hd":false},{"ty":"fl","c":{"a":0,"k":[0.336290456734,0.718559773763,0.848757755055,1],"ix":4},"o":{"a":0,"k":100,"ix":5},"r":1,"bm":0,"nm":"Fill 1","mn":"ADBE Vector Graphic - Fill","hd":false},{"ty":"tr","p":{"a":0,"k":[45.442,128.067],"ix":2},"a":{"a":0,"k":[0,0],"ix":1},"s":{"a":0,"k":[100,100],"ix":3},"r":{"a":0,"k":0,"ix":6},"o":{"a":0,"k":100,"ix":7},"sk":{"a":0,"k":0,"ix":4},"sa":{"a":0,"k":0,"ix":5},"nm":"Transform"}],"nm":"Group 1","np":4,"cix":2,"bm":0,"ix":1,"mn":"ADBE Vector Group","hd":false}],"ip":0,"op":139.000005661586,"st":-61.0000024845809,"bm":0},{"ddd":0,"ind":3,"ty":4,"nm":"Data Chart 1","sr":1,"ks":{"o":{"a":0,"k":100,"ix":11,"x":"var $bm_rt;\nvar result;\nresult = getAnimationComposerPresetValue();\nfunction getAnimationComposerPresetValue() {\n    var bL = thisLayer;\n    var tTrI = null;\n    var tTrO = null;\n    if (bL.marker.numKeys > 0) {\n        var acmp = 'zzzzzzzzzzzzzzz_AC';\n        for (var i = 1; i <= bL.marker.numKeys; i++) {\n            var m = bL.marker.key(i);\n            var p = m.parameters;\n            if (p.hasOwnProperty(acmp + 'MarkerEnabled') && p.hasOwnProperty(acmp + 'MarkerType') && p.hasOwnProperty(acmp + 'MarkerAppPresetType')) {\n                if (p[acmp + 'MarkerEnabled'] != '1') {\n                    continue;\n                }\n                switch (p[acmp + 'MarkerAppPresetType']) {\n                case '1': {\n                        tTrI = m.time;\n                        break;\n                    }\n                case '2': {\n                        tTrO = m.time;\n                        break;\n                    }\n                }\n            }\n        }\n    }\n    ;\n    function acValMul(val) {\n        acAccM *= val;\n    }\n    function easeInCubic(t) {\n        return $bm_mul($bm_mul(t, t), t);\n    }\n    function upACo(tIn, dIn, tOut, dOut, eFi, eFo) {\n        if (dIn < 0) {\n            dIn = 0;\n        }\n        if (dOut < 0) {\n            dOut = 0;\n        }\n        ac.fade = 1;\n        if (t < tOut) {\n            if (t < $bm_sum(tIn, dIn)) {\n                if (dIn == 0) {\n                    ac.fade = 0;\n                } else {\n                    ac.fade = $bm_div($bm_sub(t, tIn), dIn);\n                    if (ac.fade < 0) {\n                        ac.fade = 0;\n                    }\n                    if (ac.fade > 1) {\n                        ac.fade = 1;\n                    }\n                    if (eFi) {\n                        ac.fade = eFi(ac.fade);\n                    }\n                }\n            }\n        } else {\n            if (dOut == 0) {\n                ac.fade = 0;\n            } else {\n                ac.fade = $bm_div($bm_sub(t, tOut), dOut);\n                if (ac.fade < 0) {\n                    ac.fade = 0;\n                }\n                if (ac.fade > 1) {\n                    ac.fade = 1;\n                }\n                if (eFo) {\n                    ac.fade = eFo(ac.fade);\n                }\n                ac.fade = $bm_sub(1, ac.fade);\n            }\n        }\n        ac.intensity = 1;\n        ac.en = true;\n        ac.t = $bm_sub(t, tIn);\n    }\n    var ac = {};\n    ac.en = false;\n    var v = thisProperty.value;\n    var t = time;\n    var acAccM = 1;\n    ac.en = false;\n    if (tTrI !== null && t < tTrI) {\n        upACo(bL.inPoint, $bm_sub(tTrI, bL.inPoint), bL.outPoint, 0);\n        ac.fade = $bm_sub(1, ac.fade);\n    }\n    if (ac.en) {\n        acValMul($bm_sub(1, easeInCubic(ac.fade)));\n    }\n    ac.en = false;\n    if (tTrO !== null && t >= tTrO) {\n        upACo(0, 0, tTrO, $bm_sub($bm_sub(bL.outPoint, tTrO), thisComp.frameDuration));\n        ac.fade = $bm_sub(1, ac.fade);\n    }\n    if (ac.en) {\n        acValMul($bm_sub(1, easeInCubic(ac.fade)));\n    }\n    v = thisProperty.value;\n    v *= acAccM;\n    return v;\n}\n$bm_rt = result;"},"r":{"a":0,"k":0,"ix":10},"p":{"a":0,"k":[252,772,0],"ix":2},"a":{"a":0,"k":[45.5,60,0],"ix":1},"s":{"a":0,"k":[153.333,153.333,100],"ix":6}},"ao":0,"shapes":[{"ty":"gr","it":[{"ind":0,"ty":"sh","ix":1,"ks":{"a":0,"k":{"i":[[0,0]],"o":[[0,0]],"v":[[115.935,646.957]],"c":false},"ix":2},"nm":"Path 1","mn":"ADBE Vector Shape - Group","hd":false},{"ty":"st","c":{"a":0,"k":[1,1,1,1],"ix":3},"o":{"a":0,"k":100,"ix":4},"w":{"a":0,"k":2,"ix":5},"lc":1,"lj":1,"ml":4,"bm":0,"nm":"Stroke 1","mn":"ADBE Vector Graphic - Stroke","hd":false},{"ty":"fl","c":{"a":0,"k":[0.745626292509,0.859146836225,0.914702411726,1],"ix":4},"o":{"a":0,"k":100,"ix":5},"r":1,"bm":0,"nm":"Fill 1","mn":"ADBE Vector Graphic - Fill","hd":false},{"ty":"tr","p":{"a":0,"k":[0,0],"ix":2},"a":{"a":0,"k":[0,0],"ix":1},"s":{"a":0,"k":[100,100],"ix":3},"r":{"a":0,"k":0,"ix":6},"o":{"a":0,"k":100,"ix":7},"sk":{"a":0,"k":0,"ix":4},"sa":{"a":0,"k":0,"ix":5},"nm":"Transform"}],"nm":"Shape 1","np":3,"cix":2,"bm":0,"ix":1,"mn":"ADBE Vector Group","hd":false},{"ty":"gr","it":[{"ind":0,"ty":"sh","ix":1,"ks":{"a":0,"k":{"i":[[2.043,-0.004],[0,0],[1.445,1.445],[0.002,2.044],[0,0],[-1.445,1.445],[-2.044,0],[0,0],[-1.445,-1.444],[-0.002,-2.04],[0,0],[1.445,-1.444]],"o":[[0,0],[-2.044,-0.004],[-1.445,-1.444],[0,0],[0.002,-2.04],[1.445,-1.444],[0,0],[2.043,0],[1.445,1.445],[0,0],[-0.002,2.044],[-1.445,1.445]],"v":[[37.734,59.686],[-37.734,59.686],[-43.182,57.426],[-45.441,51.982],[-45.441,-51.986],[-43.182,-57.431],[-37.734,-59.687],[37.734,-59.687],[43.182,-57.431],[45.441,-51.986],[45.441,51.982],[43.182,57.426]],"c":true},"ix":2},"nm":"Path 1","mn":"ADBE Vector Shape - Group","hd":false},{"ind":1,"ty":"sh","ix":2,"ks":{"a":0,"k":{"i":[[0,0],[0,0],[0,0],[0,0],[0,0],[0,0]],"o":[[0,0],[0,0],[0,0],[0,0],[0,0],[0,0]],"v":[[-45.442,-59.686],[-39.072,-59.686],[45.442,-59.686],[45.442,59.686],[-45.442,59.686],[-45.442,-50.892]],"c":true},"ix":2},"nm":"Path 2","mn":"ADBE Vector Shape - Group","hd":false},{"ty":"mm","mm":4,"nm":"Merge Paths 1","mn":"ADBE Vector Filter - Merge","hd":false},{"ty":"fl","c":{"a":0,"k":[0.745626292509,0.859146836225,0.914702411726,1],"ix":4},"o":{"a":0,"k":100,"ix":5},"r":1,"bm":0,"nm":"Fill 1","mn":"ADBE Vector Graphic - Fill","hd":false},{"ty":"tr","p":{"a":0,"k":[45.442,189.805],"ix":2},"a":{"a":0,"k":[0,0],"ix":1},"s":{"a":0,"k":[100,100],"ix":3},"r":{"a":0,"k":0,"ix":6},"o":{"a":0,"k":100,"ix":7},"sk":{"a":0,"k":0,"ix":4},"sa":{"a":0,"k":0,"ix":5},"nm":"Transform"}],"nm":"Group 1","np":4,"cix":2,"bm":0,"ix":2,"mn":"ADBE Vector Group","hd":false}],"ip":0,"op":136.000005539394,"st":-61.0000024845809,"bm":0}]}],"layers":[{"ddd":0,"ind":1,"ty":0,"nm":"CAsA_Loading","refId":"comp_0","sr":1,"ks":{"o":{"a":0,"k":100,"ix":11},"r":{"a":0,"k":0,"ix":10},"p":{"a":0,"k":[960,541,0],"ix":2},"a":{"a":0,"k":[960,541,0],"ix":1},"s":{"a":0,"k":[100,100,100],"ix":6}},"ao":0,"w":1920,"h":1082,"ip":0,"op":900.000036657751,"st":0,"bm":0}],"markers":[]}